Workbook
Name AMB: #REF!
Name AMB: #REF!
Name clear: #REF!
Name clear: #REF!
Name CoEq: [1]Control_Panel!$E$12
Name cost: #REF!
Name cost: #REF!
Name costlist: [2]Data!$I$2:$I$5
Name count: #REF!
Name count: #REF!
Name countlist: [2]Data!$H$2:$H$6
Name coverage: #REF!
Name coverage: #REF!
Name coveragelist: [2]Data!$AE$2:$AE$7
Name Date: [1]Control_Panel!$E$11
Name i: #REF!
Name impact: #REF!
Name impact: #REF!
Name Loss: #REF!
Name Loss: #REF!
Name Ltg: [1]Control_Panel!$E$16
Name P_base: [1]Control_Panel!$F$20
Name P_down: [1]Control_Panel!$F$22
Name P_up: [1]Control_Panel!$F$21
Name Peril: #REF!
Name Peril: #REF!
Name Project_name: [1]Control_Panel!$E$10
Name RANGE: '[3]First Loss Scale'!$C$5:$AG$5
Name Scenario: [1]Control_Panel!$E$19
Name TargetSolvency: [1]Control_Panel!$E$13
Name Tax: [1]Control_Panel!$E$15
Name Territory: #REF!
Name Territory: #REF!
Name test: #REF!
Name test: #REF!
Name v: #REF!
Name VPs: '[4]Vulnerability Profiling'!$DE$3:$DN$10
Name Yield: [1]Control_Panel!$E$14

Sheet Infos
A1: SIM' Assurances
C4: Produit Agricole Indiciel
B6: Produit | C6: Description du produit
B7: Tarification | C7: Tarification du produit
B8: Commissions | C8: Frais de gestion, commissions de distribution, et taxes
B10: (1) | C10: CIMA H
B11: (2) | C11: Modele et donnees historiques 2001 - 2024: Africa Risk View
B12: (3) | C12: Demographie & Departements - CI

Sheet Produit
A1: SIM' Assurances
C5: Produit Agricole Indiciel
C7: Type | D7: Contrat Agricole Indiciel
C8: Garanties | D8: En cas de forte sécheresse - moins de 75% de la valeur de référence de l'indice WRSI: indemnisation forfaitaire de 100.000 fcfa
D9: En cas de moyenne sécheresse - entre 76% et 85% de la valeur de référence de l'indice WRSI: indemnité forfaitaire de 50.000 fcfa
D10: En cas de faible sécheresse - entre 86% et 95% de la valeur de référence de l'indice WRSI: indemnité forfaitaire de 10.000 fcfa
D11: En cas de décès du producteur : paiement du capital de 100.000 fcfa à la famille du producteur.
C12: Définitions | D12: WRSI: indice de sécheresse défini par la FAO et publié par ARC (l'organisme assureur de l'Union Africaine) pour chaque région de la Côte d'Ivoire; la valeur de référence est la médiane des valeurs des cinq dernières années de l'indice pour une localité donnée.
D13: Région: région d'activités de l'Assuré
C14: Données | D14: Les données proviennent du satelitte CHIRP
C15: Spéculations | D15: Maïs, Mil, Sorgho
C16: Type de prime | D16: Prime unique
C17: Période de cotisation | D17: Paiement des primes entre le XXXXXX et le XXXXXX
C18: Date d'effet | D18: Date de paiement de l'intégralité de la prime. Remboursement de la prime sans prise d'effet des garanties en cas de non paiement de la cotisation au XXXXXXX
C19: Date d'expiration | D19: Paiement automatique a l'Assuré du montant garanti selon le niveau de l'indice le 31 Décembre
C20: Forme de la police | D20: A la souscription de la police, l'Assureur transmet à l'Assuré: - une carte d'assurance (conditions générales et conditions particulières) - un certificat d'adhésion par SMS ou mail (numéro d'Assuré, nom, prénom, date d'expiration)

Sheet Tarification
A1: SIM' Assurances
C5: Tarification
C7: Garanties | G7: % indemnisation | H7: % baisse de l'indice
C8: 1. Faible secheresse | D8: =+G8*D10 -> 50000 | E8: FCFA | F8: a | G8: 0.2 | H8: 0.95
C9: 2. Moyenne secheresse | D9: =G9*D10 -> 125000 | E9: FCFA | F9: b | G9: 0.5 | H9: 0.85
C10: 3. Forte secheresse | D10: 250000 | E10: FCFA | F10: c | G10: 1 | H10: 0.75
C11: 4. Décès de l'agriculteur | D11: 250000 | E11: FCFA | F11: d
C12: Prime de risque annuelle secheresse | D12: =+'(2) ARV Model'!$AQ$3 -> 9819.4847 | F12: e = p x a + q x (b - a) + r x (c - b)
C13: Prime de risque annuelle deces | D13: =D31*D11 -> 1317.8107 | F13: f = s x c
C14: Chargement pour distribution | D14: 0.22 | F14: g
C15: Marge et frais de l'assureur | D15: 0.4 | F15: h
C16: Prime commerciale annuelle HT - Secheresse | D16: =D12/(1-D14-D15) -> 25840.749 | F16: i = e / ( 1 - g - h)
C17: Prime commerciale annuelle HT - DC | D17: =D13/(1-D14-D15) -> 3467.9228 | F17: j = f / ( 1 - g - h)
C18: Taxes - Secheresse | D18: =+Commissions!D14 -> 0.0725 | F18: k
C19: Prime commerciale annuelle TTC | D19: =D16*(1+D18)+D17 -> 31182.126 | F19: l = i x ( 1 + k ) + j
C20: Taux de prime | D20: =SUM(D17,D16)/(D10+D11) -> 0.058617344 | F20: m = ( i + j ) / c
C21: Taux de sinistres | D21: =(D12+D13)/(D10+D11) -> 0.022274591 | F21: n = ( e + f ) / c
C22: Ratio S/P | D22: =D21/D20 -> 0.38 | F22: o = n / m
C23: Vente | D23: =(ROUND(D19/1000,1)+0.1)*1000 -> 31300
C26: Frequence
C28: --- faible secheresse | D28: =+'(2) ARV Model'!$AU$3 -> 0.13071634 | F28: p ---> Modele ARV
C29: --- moyenne secheresse | D29: =+'(2) ARV Model'!$AV$3 -> 0.036576865 | F29: q ---> Modele ARV
C30: --- forte secheresse | D30: =+'(2) ARV Model'!$AW$3 -> 0.0043232243 | F30: r ---> Modele ARV
C31: --- DC | D31: =+'(1) CIMA H'!G58 -> 0.0052712427 | F31: s ---> TD CIMA 45 ans
C32: Frequence totale secheresse | D32: =(D28*D8+D29*(D9-D8)+D30*(D10-D9))/D10 -> 0.039277939 | F32: t = (p x a + q x ( b - a ) + r x ( c - b ) ) / c
C33: Frequence totale Deces | D33: =D31 -> 0.0052712427 | F33: u = s

Sheet Commissions
A1: SIM' Assurances
C5: Commissions & Frais
E7: Trimestre 1 | F7: Trimestre 2 | G7: Trimestre 3 | H7: Trimestre 4
C8: Commission Distribution | D8: =SUM(E8:H8)/4 -> 0.27 | E8: 0.27 | F8: =+E8 -> 0.27 | G8: =+F8 -> 0.27 | H8: =+G8 -> 0.27
C10: Chargement pour distribution | D10: =SUM(E10:H10)/4 -> 0.27 | E10: =E9+E8 -> 0.27 | F10: =F9+F8 -> 0.27 | G10: =G9+G8 -> 0.27 | H10: =H9+H8 -> 0.27
C12: Reprises de commissions | D12: NA
C14: Taxes | D14: 0.0725
D16: Source : | E16: https://www.dgi.gouv.ci/assets/documents/LE%20SYSTEME%20FISCAL%20IVOIRIEN.pdf

Sheet (1) CIMA H
D9: Table de mortalité CIMA H
E12: Age | F12: Lx (CIMA H) | G12: qx (CIMA H) | H12: dx (CIMA H)
E13: 0 | F13: 1000000 | G13: =IF(F13=0,1,H13/F13) -> 0.0053677459 | H13: =+F13-F14 -> 5367.7459
E14: 1 | F14: 994632.25 | G14: =IF(F14=0,1,H14/F14) -> 0.00073000062 | H14: =+F14-F15 -> 726.08216
E15: 2 | F15: 993906.17 | G15: =IF(F15=0,1,H15/F15) -> 0.00055885073 | H15: =+F15-F16 -> 555.44519
E16: 3 | F16: 993350.73 | G16: =IF(F16=0,1,H16/F16) -> 0.00047618671 | H16: =+F16-F17 -> 473.02041
E17: 4 | F17: 992877.71 | G17: =IF(F17=0,1,H17/F17) -> 0.00040704388 | H17: =+F17-F18 -> 404.1448
E18: 5 | F18: 992473.56 | G18: =IF(F18=0,1,H18/F18) -> 0.00037124919 | H18: =+F18-F19 -> 368.455
E19: 6 | F19: 992105.11 | G19: =IF(F19=0,1,H19/F19) -> 0.0003344483 | H19: =+F19-F20 -> 331.80786
E20: 7 | F20: 991773.3 | G20: =IF(F20=0,1,H20/F20) -> 0.00031563494 | H20: =+F20-F21 -> 313.03831
E21: 8 | F21: 991460.26 | G21: =IF(F21=0,1,H21/F21) -> 0.00031566727 | H21: =+F21-F22 -> 312.97155
E22: 9 | F22: 991147.29 | G22: =IF(F22=0,1,H22/F22) -> 0.00029652722 | H22: =+F22-F23 -> 293.90215
E23: 10 | F23: 990853.39 | G23: =IF(F23=0,1,H23/F23) -> 0.00031572945 | H23: =+F23-F24 -> 312.84159
E24: 11 | F24: 990540.55 | G24: =IF(F24=0,1,H24/F24) -> 0.00031576179 | H24: =+F24-F25 -> 312.77486
... E123: 110 | F123: 0 | G123: =IF(F123=0,1,H123/F123) -> 1 | H123: =+F123-F124 -> 0

Sheet (2) ARV Model
B1: SIM' Assurances
G2: Source population agricole | H2: https://agriculture.gouv.fr/cote-divoire-contexte-agricole-et-relations-internationales#:~:text=La%20population%20ivoirienne%20se%20partage,deux%20tiers%20de%20la%20population. | AU2: Faible | AV2: Moy | AW2: Forte
G3: Tx population agricole | H3: 0.46 | AQ3: =SUMPRODUCT(AQ583:AQ859, $G$8:$G$284)/SUM($G$8:$G$284) -> 9819.4847 | AU3: =SUMPRODUCT(AS293:AS569, $H$8:$H$284)/SUM($H$8:$H$284) -> 0.13071634 | AV3: =SUMPRODUCT(AT293:AT569, $H$8:$H$284)/SUM($H$8:$H$284) -> 0.036576865 | AW3: =SUMPRODUCT(AU293:AU569, $H$8:$H$284)/SUM($H$8:$H$284) -> 0.0043232243
I5: Triggers | Q5: WRSI - Valeurs observées 2001-2020
I6: Faible | J6: Moyen | K6: Forte | R6: 3 | S6: 4 | T6: 5 | U6: 6 | V6: 7 | W6: 8 | X6: 9 | Y6: 10 | Z6: 11 | AA6: 12 | AB6: 13 | AC6: 14 | AD6: 15 | AE6: 16 | AF6: 17 | AG6: 18 | AH6: 19 | AI6: 20 | AJ6: 21 | AK6: 22 | AL6: 23 | AM6: 24 | AN6: 25
C7: Country | D7: Region | E7: District | F7: Sous prefectures | G7: Population Totale | H7: Population agricole | I7: 1er déclenchement | J7: 2e déclenchement | K7: 3e déclenchement | N7: Region | O7: District | P7: Sous prefectures | Q7: 2001 | R7: 2002 | S7: 2003 | T7: 2004 | U7: 2005 | V7: 2006 | W7: 2007 | X7: 2008 | Y7: 2009 | Z7: 2010 | AA7: 2011 | AB7: 2012 | AC7: 2013 | AD7: 2014 | AE7: 2015 | AF7: 2016 | AG7: 2017 | AH7: 2018 | AI7: 2019 | AJ7: 2020 | AK7: 2021 | AL7: 2022 | AM7: 2023 | AN7: 2024
C8: COTE D'IVOIRE | D8: Centre | E8: DIMBOKRO | F8: Abigui | G8: =VLOOKUP(F8,'(3) Demographie & Departements'!$G$8:$J$526,4,0) -> 8665.3727 | H8: =$H$3*G8 -> 3986.0714 | I8: =Tarification!$H$8 -> 0.95 | J8: =Tarification!$H$9 -> 0.85 | K8: =Tarification!$H$10 -> 0.75 | N8: Centre | O8: DIMBOKRO | P8: Abigui | Q8: 100 | R8: 100 | S8: 100 | T8: 100 | U8: 100 | V8: 100 | W8: 100 | X8: 100 | Y8: 100 | Z8: 100 | AA8: 100 | AB8: 100 | AC8: 100 | AD8: 100 | AE8: 100 | AF8: 100 | AG8: 100 | AH8: 100 | AI8: 100 | AJ8: 100 | AK8: 100 | AL8: 100 | AM8: 100 | AN8: 100
C9: COTE D'IVOIRE | D9: Centre | E9: OUELLE | F9: Akpassanou | G9: =VLOOKUP(F9,'(3) Demographie & Departements'!$G$8:$J$526,4,0) -> 5693.1684 | H9: =$H$3*G9 -> 2618.8575 | I9: =I8 -> 0.95 | J9: =J8 -> 0.85 | K9: =K8 -> 0.75 | N9: Centre | O9: OUELLE | P9: Akpassanou | Q9: 100 | R9: 99.70904 | S9: 100 | T9: 99.816795 | U9: 99.699901 | V9: 100 | W9: 90.869026 | X9: 100 | Y9: 98.890445 | Z9: 99.502109 | AA9: 95.076262 | AB9: 100 | AC9: 100 | AD9: 100 | AE9: 85.752635 | AF9: 99.849028 | AG9: 100 | AH9: 99.560979 | AI9: 99.762925 | AJ9: 100 | AK9: 99.530486 | AL9: 100 | AM9: 100 | AN9: 98.055896
C10: COTE D'IVOIRE | D10: Centre | E10: TANDA | F10: Amanvi | G10: =VLOOKUP(F10,'(3) Demographie & Departements'!$G$8:$J$526,4,0) -> 10140.78 | H10: =$H$3*G10 -> 4664.7588 | I10: =I9 -> 0.95 | J10: =J9 -> 0.85 | K10: =K9 -> 0.75 | N10: Centre | O10: TANDA | P10: Amanvi | Q10: 100 | R10: 100 | S10: 100 | T10: 87.264303 | U10: 92.57711 | V10: 100 | W10: 95.249777 | X10: 100 | Y10: 100 | Z10: 100 | AA10: 100 | AB10: 100 | AC10: 90.566277 | AD10: 100 | AE10: 76.92464 | AF10: 93.993674 | AG10: 100 | AH10: 99.517981 | AI10: 100 | AJ10: 100 | AK10: 99.653128 | AL10: 100 | AM10: 100 | AN10: 99.978249
C11: COTE D'IVOIRE | D11: Centre | E11: OUELLE | F11: Ananda | G11: =VLOOKUP(F11,'(3) Demographie & Departements'!$G$8:$J$526,4,0) -> 13166.288 | H11: =$H$3*G11 -> 6056.4923 | I11: =I10 -> 0.95 | J11: =J10 -> 0.85 | K11: =K10 -> 0.75 | N11: Centre | O11: OUELLE | P11: Ananda | Q11: 100 | R11: 100 | S11: 100 | T11: 99.956049 | U11: 100 | V11: 100 | W11: 92.364238 | X11: 100 | Y11: 100 | Z11: 99.925044 | AA11: 98.874753 | AB11: 100 | AC11: 100 | AD11: 100 | AE11: 89.348607 | AF11: 100 | AG11: 100 | AH11: 100 | AI11: 100 | AJ11: 100 | AK11: 100 | AL11: 100 | AM11: 100 | AN11: 99.938185
C12: COTE D'IVOIRE | D12: Centre | E12: BONGOUANOU | F12: Ande | G12: =VLOOKUP(F12,'(3) Demographie & Departements'!$G$8:$J$526,4,0) -> 58286.682 | H12: =$H$3*G12 -> 26811.873 | I12: =I11 -> 0.95 | J12: =J11 -> 0.85 | K12: =K11 -> 0.75 | N12: Centre | O12: BONGOUANOU | P12: Ande | Q12: 100 | R12: 100 | S12: 100 | T12: 100 | U12: 100 | V12: 100 | W12: 100 | X12: 100 | Y12: 100 | Z12: 100 | AA12: 100 | AB12: 100 | AC12: 100 | AD12: 100 | AE12: 100 | AF12: 100 | AG12: 100 | AH12: 100 | AI12: 100 | AJ12: 100 | AK12: 100 | AL12: 100 | AM12: 100 | AN12: 99.222583
C13: COTE D'IVOIRE | D13: Centre | E13: BEOUMI | F13: Ando-Kekrenou | G13: =VLOOKUP(F13,'(3) Demographie & Departements'!$G$8:$J$526,4,0) -> 16825.632 | H13: =$H$3*G13 -> 7739.7909 | I13: =I12 -> 0.95 | J13: =J12 -> 0.85 | K13: =K12 -> 0.75 | N13: Centre | O13: BEOUMI | P13: Ando-Kekrenou | Q13: 100 | R13: 100 | S13: 99.817994 | T13: 100 | U13: 98.756442 | V13: 100 | W13: 92.058464 | X13: 100 | Y13: 98.929726 | Z13: 98.559833 | AA13: 97.673561 | AB13: 100 | AC13: 100 | AD13: 100 | AE13: 89.135152 | AF13: 99.152723 | AG13: 100 | AH13: 99.814677 | AI13: 96.493868 | AJ13: 99.141929 | AK13: 99.576943 | AL13: 99.686531 | AM13: 100 | AN13: 92.82755
C14: COTE D'IVOIRE | D14: Centre | E14: TOUMODI | F14: Angoda | G14: =VLOOKUP(F14,'(3) Demographie & Departements'!$G$8:$J$526,4,0) -> 11818.835 | H14: =$H$3*G14 -> 5436.6639 | I14: =I13 -> 0.95 | J14: =J13 -> 0.85 | K14: =K13 -> 0.75 | N14: Centre | O14: TOUMODI | P14: Angoda | Q14: 100 | R14: 100 | S14: 100 | T14: 100 | U14: 100 | V14: 100 | W14: 100 | X14: 100 | Y14: 100 | Z14: 100 | AA14: 100 | AB14: 100 | AC14: 100 | AD14: 100 | AE14: 100 | AF14: 100 | AG14: 100 | AH14: 100 | AI14: 100 | AJ14: 100 | AK14: 100 | AL14: 100 | AM14: 100 | AN14: 100
C15: COTE D'IVOIRE | D15: Centre | E15: PRIKRO | F15: Anianou | G15: =VLOOKUP(F15,'(3) Demographie & Departements'!$G$8:$J$526,4,0) -> 7956.2094 | H15: =$H$3*G15 -> 3659.8563 | I15: =I14 -> 0.95 | J15: =J14 -> 0.85 | K15: =K14 -> 0.75 | N15: Centre | O15: PRIKRO | P15: Anianou | Q15: 100 | R15: 100 | S15: 100 | T15: 91.118567 | U15: 91.167471 | V15: 100 | W15: 93.354219 | X15: 100 | Y15: 99.987177 | Z15: 100 | AA15: 100 | AB15: 100 | AC15: 100 | AD15: 100 | AE15: 86.299556 | AF15: 88.682365 | AG15: 99.597557 | AH15: 98.516627 | AI15: 99.31649 | AJ15: 100 | AK15: 98.911061 | AL15: 98.347001 | AM15: 100 | AN15: 85.203439
C16: COTE D'IVOIRE | D16: Centre | E16: M'BATTO | F16: Anoumaba | G16: =VLOOKUP(F16,'(3) Demographie & Departements'!$G$8:$J$526,4,0) -> 22571.867 | H16: =$H$3*G16 -> 10383.059 | I16: =I15 -> 0.95 | J16: =J15 -> 0.85 | K16: =K15 -> 0.75 | N16: Centre | O16: M'BATTO | P16: Anoumaba | Q16: 100 | R16: 100 | S16: 100 | T16: 100 | U16: 100 | V16: 100 | W16: 100 | X16: 100 | Y16: 100 | Z16: 100 | AA16: 100 | AB16: 100 | AC16: 100 | AD16: 100 | AE16: 100 | AF16: 100 | AG16: 100 | AH16: 100 | AI16: 100 | AJ16: 100 | AK16: 100 | AL16: 100 | AM16: 100 | AN16: 100
C17: COTE D'IVOIRE | D17: Centre | E17: BONDOUKOU | F17: Appimadoum | G17: =VLOOKUP(F17,'(3) Demographie & Departements'!$G$8:$J$526,4,0) -> 9919.5338 | H17: =$H$3*G17 -> 4562.9855 | I17: =I16 -> 0.95 | J17: =J16 -> 0.85 | K17: =K16 -> 0.75 | N17: Centre | O17: BONDOUKOU | P17: Appimadoum | Q17: 100 | R17: 100 | S17: 100 | T17: 92.135986 | U17: 100 | V17: 100 | W17: 100 | X17: 100 | Y17: 100 | Z17: 100 | AA17: 100 | AB17: 100 | AC17: 97.575032 | AD17: 100 | AE17: 90.180961 | AF17: 100 | AG17: 100 | AH17: 100 | AI17: 100 | AJ17: 100 | AK17: 100 | AL17: 100 | AM17: 100 | AN17: 100
C18: COTE D'IVOIRE | D18: Centre | E18: ARRAH | F18: Arrah | G18: =VLOOKUP(F18,'(3) Demographie & Departements'!$G$8:$J$526,4,0) -> 45625.37 | H18: =$H$3*G18 -> 20987.67 | I18: =I17 -> 0.95 | J18: =J17 -> 0.85 | K18: =K17 -> 0.75 | N18: Centre | O18: ARRAH | P18: Arrah | Q18: 100 | R18: 100 | S18: 100 | T18: 100 | U18: 100 | V18: 100 | W18: 100 | X18: 100 | Y18: 100 | Z18: 100 | AA18: 100 | AB18: 100 | AC18: 100 | AD18: 100 | AE18: 100 | AF18: 99.964311 | AG18: 100 | AH18: 100 | AI18: 100 | AJ18: 100 | AK18: 100 | AL18: 100 | AM18: 100 | AN18: 96.026325
C19: COTE D'IVOIRE | D19: Centre | E19: M'BATTO | F19: Assahara | G19: =VLOOKUP(F19,'(3) Demographie & Departements'!$G$8:$J$526,4,0) -> 11495.068 | H19: =$H$3*G19 -> 5287.7311 | I19: =I18 -> 0.95 | J19: =J18 -> 0.85 | K19: =K18 -> 0.75 | N19: Centre | O19: M'BATTO | P19: Assahara | Q19: 100 | R19: 100 | S19: 100 | T19: 100 | U19: 100 | V19: 100 | W19: 100 | X19: 100 | Y19: 100 | Z19: 100 | AA19: 100 | AB19: 100 | AC19: 100 | AD19: 100 | AE19: 100 | AF19: 100 | AG19: 100 | AH19: 100 | AI19: 100 | AJ19: 100 | AK19: 100 | AL19: 100 | AM19: 100 | AN19: 100
C20: COTE D'IVOIRE | D20: Centre | E20: BONGOUANOU | F20: Assie-Koumassi | G20: =VLOOKUP(F20,'(3) Demographie & Departements'!$G$8:$J$526,4,0) -> 21961.698 | H20: =$H$3*G20 -> 10102.381 | I20: =I19 -> 0.95 | J20: =J19 -> 0.85 | K20: =K19 -> 0.75 | N20: Centre | O20: BONGOUANOU | P20: Assie-Koumassi | Q20: 100 | R20: 100 | S20: 100 | T20: 100 | U20: 100 | V20: 100 | W20: 99.852603 | X20: 100 | Y20: 100 | Z20: 100 | AA20: 100 | AB20: 100 | AC20: 100 | AD20: 100 | AE20: 99.49304 | AF20: 100 | AG20: 100 | AH20: 100 | AI20: 100 | AJ20: 100 | AK20: 100 | AL20: 100 | AM20: 100 | AN20: 98.725415
... C242: COTE D'IVOIRE | D242: Nord | E242: TENGRELA | F242: Papara | G242: =VLOOKUP(F242,'(3) Demographie & Departements'!$G$8:$J$526,4,0) -> 13448.441 | H242: =$H$3*G242 -> 6186.283 | I242: =I241 -> 0.95 | J242: =J241 -> 0.85 | K242: =K241 -> 0.75 | N242: Nord | O242: TENGRELA | P242: Papara | Q242: 100 | R242: 100 | S242: 100 | T242: 92.86841 | U242: 100 | V242: 100 | W242: 100 | X242: 100 | Y242: 100 | Z242: 100 | AA242: 100 | AB242: 100 | AC242: 100 | AD242: 95.190813 | AE242: 99.523082 | AF242: 99.689782 | AG242: 100 | AH242: 100 | AI242: 99.746752 | AJ242: 97.430079 | AK242: 100 | AL242: 100 | AM242: 100 | AN242: 100
C243: COTE D'IVOIRE | D243: Nord | E243: 1 | F243: Parc National de Bouna | G243: 10000 | H243: =$H$3*G243 -> 4600 | I243: =I242 -> 0.95 | J243: =J242 -> 0.85 | K243: =K242 -> 0.75 | N243: Nord | O243: 1 | P243: Parc National de Bouna | Q243: 91.333459 | R243: 99.700933 | S243: 92.800784 | T243: 90.001411 | U243: 91.620959 | V243: 98.327544 | W243: 90.8785 | X243: 99.999562 | Y243: 98.784294 | Z243: 96.172963 | AA243: 99.959454 | AB243: 99.453858 | AC243: 84.360097 | AD243: 86.939893 | AE243: 90.331896 | AF243: 94.283878 | AG243: 90.735154 | AH243: 96.107808 | AI243: 98.820811 | AJ243: 87.669908 | AK243: 99.994716 | AL243: 98.986913 | AM243: 99.648759 | AN243: 82.872726
C244: COTE D'IVOIRE | D244: Nord | E244: SINEMATIALI | F244: Sediogo | G244: =VLOOKUP(F244,'(3) Demographie & Departements'!$G$8:$J$526,4,0) -> 6599.7005 | H244: =$H$3*G244 -> 3035.8622 | I244: =I243 -> 0.95 | J244: =J243 -> 0.85 | K244: =K243 -> 0.75 | N244: Nord | O244: SINEMATIALI | P244: Sediogo | Q244: 100 | R244: 100 | S244: 100 | T244: 99.362876 | U244: 100 | V244: 100 | W244: 100 | X244: 100 | Y244: 100 | Z244: 100 | AA244: 100 | AB244: 100 | AC244: 100 | AD244: 89.873846 | AE244: 100 | AF244: 99.306361 | AG244: 100 | AH244: 100 | AI244: 97.825246 | AJ244: 92.482438 | AK244: 100 | AL244: 100 | AM244: 100 | AN244: 100
C245: COTE D'IVOIRE | D245: Nord | E245: SEGUELA | F245: Seguela | G245: =VLOOKUP(F245,'(3) Demographie & Departements'!$G$8:$J$526,4,0) -> 103979.63 | H245: =$H$3*G245 -> 47830.632 | I245: =I244 -> 0.95 | J245: =J244 -> 0.85 | K245: =K244 -> 0.75 | N245: Nord | O245: SEGUELA | P245: Seguela | Q245: 89.209121 | R245: 100 | S245: 100 | T245: 83.915639 | U245: 96.028324 | V245: 99.675341 | W245: 87.330561 | X245: 100 | Y245: 98.402409 | Z245: 93.285717 | AA245: 87.391118 | AB245: 99.587679 | AC245: 95.947839 | AD245: 86.593274 | AE245: 88.588476 | AF245: 76.752653 | AG245: 90.645862 | AH245: 99.734677 | AI245: 94.227843 | AJ245: 87.374 | AK245: 100 | AL245: 96.100991 | AM245: 100 | AN245: 90.651856
C246: COTE D'IVOIRE | D246: Nord | E246: SEGUELON | F246: Seguelon | G246: =VLOOKUP(F246,'(3) Demographie & Departements'!$G$8:$J$526,4,0) -> 21213.267 | H246: =$H$3*G246 -> 9758.1027 | I246: =I245 -> 0.95 | J246: =J245 -> 0.85 | K246: =K245 -> 0.75 | N246: Nord | O246: SEGUELON | P246: Seguelon | Q246: 100 | R246: 100 | S246: 100 | T246: 100 | U246: 100 | V246: 100 | W246: 100 | X246: 100 | Y246: 100 | Z246: 100 | AA246: 100 | AB246: 100 | AC246: 100 | AD246: 100 | AE246: 99.972608 | AF246: 100 | AG246: 100 | AH246: 100 | AI246: 100 | AJ246: 100 | AK246: 100 | AL246: 100 | AM246: 100 | AN246: 100
C247: COTE D'IVOIRE | D247: Nord | E247: OUANINOU | F247: Saboudougou | G247: =VLOOKUP(F247,'(3) Demographie & Departements'!$G$8:$J$526,4,0) -> 5225.2745 | H247: =$H$3*G247 -> 2403.6263 | I247: =I246 -> 0.95 | J247: =J246 -> 0.85 | K247: =K246 -> 0.75 | N247: Nord | O247: OUANINOU | P247: Saboudougou | Q247: 100 | R247: 100 | S247: 100 | T247: 100 | U247: 100 | V247: 100 | W247: 100 | X247: 100 | Y247: 100 | Z247: 100 | AA247: 100 | AB247: 100 | AC247: 100 | AD247: 100 | AE247: 100 | AF247: 100 | AG247: 100 | AH247: 100 | AI247: 100 | AJ247: 100 | AK247: 100 | AL247: 100 | AM247: 100 | AN247: 100
C248: COTE D'IVOIRE | D248: Nord | E248: GBELEBAN | F248: Samango | G248: =VLOOKUP(F248,'(3) Demographie & Departements'!$G$8:$J$526,4,0) -> 17218.821 | H248: =$H$3*G248 -> 7920.6577 | I248: =I247 -> 0.95 | J248: =J247 -> 0.85 | K248: =K247 -> 0.75 | N248: Nord | O248: GBELEBAN | P248: Samango | Q248: 100 | R248: 100 | S248: 100 | T248: 100 | U248: 100 | V248: 100 | W248: 100 | X248: 100 | Y248: 100 | Z248: 100 | AA248: 100 | AB248: 100 | AC248: 100 | AD248: 100 | AE248: 100 | AF248: 100 | AG248: 100 | AH248: 100 | AI248: 100 | AJ248: 100 | AK248: 100 | AL248: 100 | AM248: 100 | AN248: 100
C249: COTE D'IVOIRE | D249: Nord | E249: SAMATIGUILA | F249: Samatiguila | G249: =VLOOKUP(F249,'(3) Demographie & Departements'!$G$8:$J$526,4,0) -> 7777.0846 | H249: =$H$3*G249 -> 3577.4589 | I249: =I248 -> 0.95 | J249: =J248 -> 0.85 | K249: =K248 -> 0.75 | N249: Nord | O249: SAMATIGUILA | P249: Samatiguila | Q249: 100 | R249: 100 | S249: 100 | T249: 100 | U249: 100 | V249: 100 | W249: 100 | X249: 100 | Y249: 100 | Z249: 100 | AA249: 100 | AB249: 100 | AC249: 100 | AD249: 100 | AE249: 100 | AF249: 100 | AG249: 100 | AH249: 100 | AI249: 100 | AJ249: 100 | AK249: 100 | AL249: 100 | AM249: 100 | AN249: 100
C250: COTE D'IVOIRE | D250: Centre | E250: SANDEGUE | F250: Sandegue | G250: =VLOOKUP(F250,'(3) Demographie & Departements'!$G$8:$J$526,4,0) -> 26917.944 | H250: =$H$3*G250 -> 12382.254 | I250: =I249 -> 0.95 | J250: =J249 -> 0.85 | K250: =K249 -> 0.75 | N250: Centre | O250: SANDEGUE | P250: Sandegue | Q250: 79.004428 | R250: 99.699542 | S250: 84.799858 | T250: 71.390933 | U250: 70.928668 | V250: 93.094512 | W250: 81.830857 | X250: 100 | Y250: 84.451566 | Z250: 100 | AA250: 100 | AB250: 100 | AC250: 79.092851 | AD250: 75.526015 | AE250: 70.354035 | AF250: 66.856554 | AG250: 93.700516 | AH250: 73.67492 | AI250: 97.43368 | AJ250: 82.720459 | AK250: 99.634895 | AL250: 93.948774 | AM250: 100 | AN250: 74.76458
C251: COTE D'IVOIRE | D251: Nord | E251: BIANKOUMA | F251: SANTA-BIANKOUMA | G251: =VLOOKUP(F251,'(3) Demographie & Departements'!$G$8:$J$526,4,0) -> 51818.758 | H251: =$H$3*G251 -> 23836.629 | I251: =I250 -> 0.95 | J251: =J250 -> 0.85 | K251: =K250 -> 0.75 | N251: Nord | O251: BIANKOUMA | P251: SANTA-BIANKOUMA | Q251: 100 | R251: 100 | S251: 100 | T251: 100 | U251: 100 | V251: 100 | W251: 100 | X251: 100 | Y251: 100 | Z251: 100 | AA251: 100 | AB251: 100 | AC251: 100 | AD251: 100 | AE251: 100 | AF251: 100 | AG251: 100 | AH251: 100 | AI251: 100 | AJ251: 100 | AK251: 100 | AL251: 100 | AM251: 100 | AN251: 100
C252: COTE D'IVOIRE | D252: Nord | E252: MANKONO | F252: Sarhala | G252: =VLOOKUP(F252,'(3) Demographie & Departements'!$G$8:$J$526,4,0) -> 42450.425 | H252: =$H$3*G252 -> 19527.196 | I252: =I251 -> 0.95 | J252: =J251 -> 0.85 | K252: =K251 -> 0.75 | N252: Nord | O252: MANKONO | P252: Sarhala | Q252: 90.272978 | R252: 99.841572 | S252: 80.554481 | T252: 75.701859 | U252: 90.218932 | V252: 88.648751 | W252: 80.882222 | X252: 99.945145 | Y252: 89.67926 | Z252: 71.435811 | AA252: 88.875573 | AB252: 100 | AC252: 99.371248 | AD252: 79.102726 | AE252: 74.166182 | AF252: 82.593397 | AG252: 82.279744 | AH252: 90.84944 | AI252: 84.598807 | AJ252: 86.813691 | AK252: 88.325483 | AL252: 99.708998 | AM252: 97.10997 | AN252: 85.490111
C253: COTE D'IVOIRE | D253: Nord | E253: DABAKALA | F253: Satama-Sokoro | G253: =VLOOKUP(F253,'(3) Demographie & Departements'!$G$8:$J$526,4,0) -> 26162.873 | H253: =$H$3*G253 -> 12034.922 | I253: =I252 -> 0.95 | J253: =J252 -> 0.85 | K253: =K252 -> 0.75 | N253: Nord | O253: DABAKALA | P253: Satama-Sokoro | Q253: 78.473866 | R253: 95.593037 | S253: 82.529412 | T253: 85.853236 | U253: 71.365731 | V253: 89.538597 | W253: 91.274767 | X253: 100 | Y253: 87.364989 | Z253: 90.829496 | AA253: 91.421124 | AB253: 91.780095 | AC253: 74.652271 | AD253: 72.245758 | AE253: 70.596851 | AF253: 65.272497 | AG253: 93.835114 | AH253: 93.92181 | AI253: 87.37377 | AJ253: 74.115436 | AK253: 100 | AL253: 99.478899 | AM253: 94.352173 | AN253: 81.820732
C254: COTE D'IVOIRE | D254: Nord | E254: DABAKALA | F254: Satama-Sokoura | G254: =VLOOKUP(F254,'(3) Demographie & Departements'!$G$8:$J$526,4,0) -> 13066.55 | H254: =$H$3*G254 -> 6010.6131 | I254: =I253 -> 0.95 | J254: =J253 -> 0.85 | K254: =K253 -> 0.75 | N254: Nord | O254: DABAKALA | P254: Satama-Sokoura | Q254: 75.382831 | R254: 93.214101 | S254: 81.118369 | T254: 92.19986 | U254: 70.230293 | V254: 90.276192 | W254: 88.948511 | X254: 100 | Y254: 87.93062 | Z254: 94.744696 | AA254: 92.094551 | AB254: 92.988773 | AC254: 72.382869 | AD254: 70.546689 | AE254: 71.371882 | AF254: 62.052121 | AG254: 95.72677 | AH254: 93.123289 | AI254: 82.994977 | AJ254: 69.927547 | AK254: 100 | AL254: 95.587951 | AM254: 92.239661 | AN254: 81.909809
C255: COTE D'IVOIRE | D255: Nord | E255: GBELEBAN | F255: Seydougou | G255: =VLOOKUP(F255,'(3) Demographie & Departements'!$G$8:$J$526,4,0) -> 7806.2264 | H255: =$H$3*G255 -> 3590.8641 | I255: =I254 -> 0.95 | J255: =J254 -> 0.85 | K255: =K254 -> 0.75 | N255: Nord | O255: GBELEBAN | P255: Seydougou | Q255: 100 | R255: 100 | S255: 100 | T255: 100 | U255: 100 | V255: 100 | W255: 100 | X255: 100 | Y255: 100 | Z255: 100 | AA255: 100 | AB255: 100 | AC255: 100 | AD255: 100 | AE255: 100 | AF255: 100 | AG255: 100 | AH255: 100 | AI255: 100 | AJ255: 100 | AK255: 100 | AL255: 100 | AM255: 100 | AN255: 100
... C284: COTE D'IVOIRE | D284: Nord | E284: BOUNA | F284: Youndouo | G284: =VLOOKUP(F284,'(3) Demographie & Departements'!$G$8:$J$526,4,0) -> 24825.647 | H284: =$H$3*G284 -> 11419.798 | I284: =I283 -> 0.95 | J284: =J283 -> 0.85 | K284: =K283 -> 0.75 | N284: Nord | O284: BOUNA | P284: Youndouo | Q284: 86.834677 | R284: 100 | S284: 87.944217 | T284: 92.080398 | U284: 95.604482 | V284: 95.811729 | W284: 93.639523 | X284: 100 | Y284: 100 | Z284: 98.540059 | AA284: 99.944237 | AB284: 99.857084 | AC284: 75.096378 | AD284: 91.69211 | AE284: 81.255202 | AF284: 92.601345 | AG284: 86.058812 | AH284: 85.759544 | AI284: 99.500967 | AJ284: 88.850773 | AK284: 100 | AL284: 99.384919 | AM284: 100 | AN284: 82.063109
M291: WRSI - deviations 2001-2020 | AS291: Frequences (Cumulatives) Secheresse: | BE291: Frequences (Specifiques) Secheresse:
N292: Region | O292: District | P292: Sous prefectures | Q292: 2001 | R292: 2002 | S292: 2003 | T292: 2004 | U292: 2005 | V292: 2006 | W292: 2007 | X292: 2008 | Y292: 2009 | Z292: 2010 | AA292: 2011 | AB292: 2012 | AC292: 2013 | AD292: 2014 | AE292: 2015 | AF292: 2016 | AG292: 2017 | AH292: 2018 | AI292: 2019 | AJ292: 2020 | AK292: 2021 | AL292: 2022 | AM292: 2023 | AN292: 2024 | AS292: >=Faible | AT292: >=Moyenne | AU292: >=Severe | AW292: Faible | AX292: Moyenne | AY292: Severe | BA292: Faible | BB292: Moyenne | BC292: Severe | BE292: Faible | BF292: Moyenne | BG292: Severe
N293: Centre | O293: DIMBOKRO | P293: Abigui | V293: =V8/MEDIAN(Q8:U8) -> 1 | W293: =W8/MEDIAN(R8:V8) -> 1 | X293: =X8/MEDIAN(S8:W8) -> 1 | Y293: =Y8/MEDIAN(T8:X8) -> 1 | Z293: =Z8/MEDIAN(U8:Y8) -> 1 | AA293: =AA8/MEDIAN(V8:Z8) -> 1 | AB293: =AB8/MEDIAN(W8:AA8) -> 1 | AC293: =AC8/MEDIAN(X8:AB8) -> 1 | ... AN293: =AN8/MEDIAN(AI8:AM8) -> 1 | AS293: {=SUMPRODUCT(($V293:$AN293<=$I8)*(1))/COUNT($V293:$AN293)} -> 0 | AT293: {=SUMPRODUCT(($V293:$AN293<=$J8)*(1))/COUNT($V293:$AN293)} -> 0 | AU293: {=SUMPRODUCT(($V293:$AN293<=$K8)*(1))/COUNT($V293:$AN293)} -> 0 | AW293: {=SUMPRODUCT(($V293:$AN293<=$I8)*(1))} -> 0 | AX293: {=SUMPRODUCT(($V293:$AN293<=$J8)*(1))} -> 0 | AY293: {=SUMPRODUCT(($V293:$AN293<=$K8)*(1))} -> 0 | BA293: =AW293-AX293 -> 0 | BB293: =AX293-AY293 -> 0 | BC293: =AY293 -> 0 | BE293: =BA293/COUNT($V293:$AN293) -> 0 | BF293: =BB293/COUNT($V293:$AN293) -> 0 | BG293: =BC293/COUNT($V293:$AN293) -> 0
N294: Centre | O294: OUELLE | P294: Akpassanou | V294: =V9/MEDIAN(Q9:U9) -> 1.0018354 | W294: =W9/MEDIAN(R9:V9) -> 0.91035808 | X294: =X9/MEDIAN(S9:W9) -> 1.0018354 | Y294: =Y9/MEDIAN(T9:X9) -> 0.9907195 | Z294: =Z9/MEDIAN(U9:Y9) -> 0.99801612 | AA294: =AA9/MEDIAN(V9:Z9) -> 0.95552007 | AB294: =AB9/MEDIAN(W9:AA9) -> 1.01122 | AC294: =AC9/MEDIAN(X9:AB9) -> 1.0050038 | ... AN294: =AN9/MEDIAN(AI9:AM9) -> 0.98055896 | AS294: {=SUMPRODUCT(($V294:$AN294<=$I9)*(1))/COUNT($V294:$AN294)} -> 0.10526316 | AT294: {=SUMPRODUCT(($V294:$AN294<=$J9)*(1))/COUNT($V294:$AN294)} -> 0 | AU294: {=SUMPRODUCT(($V294:$AN294<=$K9)*(1))/COUNT($V294:$AN294)} -> 0 | AW294: {=SUMPRODUCT(($V294:$AN294<=$I9)*(1))} -> 2 | AX294: {=SUMPRODUCT(($V294:$AN294<=$J9)*(1))} -> 0 | AY294: {=SUMPRODUCT(($V294:$AN294<=$K9)*(1))} -> 0 | BA294: =AW294-AX294 -> 2 | BB294: =AX294-AY294 -> 0 | BC294: =AY294 -> 0 | BE294: =BA294/COUNT($V294:$AN294) -> 0.10526316 | BF294: =BB294/COUNT($V294:$AN294) -> 0 | BG294: =BC294/COUNT($V294:$AN294) -> 0
N295: Centre | O295: TANDA | P295: Amanvi | V295: =V10/MEDIAN(Q10:U10) -> 1 | W295: =W10/MEDIAN(R10:V10) -> 0.95249777 | X295: =X10/MEDIAN(S10:W10) -> 1.0498712 | Y295: =Y10/MEDIAN(T10:X10) -> 1.0498712 | Z295: =Z10/MEDIAN(U10:Y10) -> 1 | AA295: =AA10/MEDIAN(V10:Z10) -> 1 | AB295: =AB10/MEDIAN(W10:AA10) -> 1 | AC295: =AC10/MEDIAN(X10:AB10) -> 0.90566277 | ... AN295: =AN10/MEDIAN(AI10:AM10) -> 0.99978249 | AS295: {=SUMPRODUCT(($V295:$AN295<=$I10)*(1))/COUNT($V295:$AN295)} -> 0.15789474 | AT295: {=SUMPRODUCT(($V295:$AN295<=$J10)*(1))/COUNT($V295:$AN295)} -> 0.052631579 | AU295: {=SUMPRODUCT(($V295:$AN295<=$K10)*(1))/COUNT($V295:$AN295)} -> 0 | AW295: {=SUMPRODUCT(($V295:$AN295<=$I10)*(1))} -> 3 | AX295: {=SUMPRODUCT(($V295:$AN295<=$J10)*(1))} -> 1 | AY295: {=SUMPRODUCT(($V295:$AN295<=$K10)*(1))} -> 0 | BA295: =AW295-AX295 -> 2 | BB295: =AX295-AY295 -> 1 | BC295: =AY295 -> 0 | BE295: =BA295/COUNT($V295:$AN295) -> 0.10526316 | BF295: =BB295/COUNT($V295:$AN295) -> 0.052631579 | BG295: =BC295/COUNT($V295:$AN295) -> 0
N296: Centre | O296: OUELLE | P296: Ananda | V296: =V11/MEDIAN(Q11:U11) -> 1 | W296: =W11/MEDIAN(R11:V11) -> 0.92364238 | X296: =X11/MEDIAN(S11:W11) -> 1 | Y296: =Y11/MEDIAN(T11:X11) -> 1 | Z296: =Z11/MEDIAN(U11:Y11) -> 0.99925044 | AA296: =AA11/MEDIAN(V11:Z11) -> 0.98874753 | AB296: =AB11/MEDIAN(W11:AA11) -> 1.0007501 | AC296: =AC11/MEDIAN(X11:AB11) -> 1 | ... AN296: =AN11/MEDIAN(AI11:AM11) -> 0.99938185 | AS296: {=SUMPRODUCT(($V296:$AN296<=$I11)*(1))/COUNT($V296:$AN296)} -> 0.10526316 | AT296: {=SUMPRODUCT(($V296:$AN296<=$J11)*(1))/COUNT($V296:$AN296)} -> 0 | AU296: {=SUMPRODUCT(($V296:$AN296<=$K11)*(1))/COUNT($V296:$AN296)} -> 0 | AW296: {=SUMPRODUCT(($V296:$AN296<=$I11)*(1))} -> 2 | AX296: {=SUMPRODUCT(($V296:$AN296<=$J11)*(1))} -> 0 | AY296: {=SUMPRODUCT(($V296:$AN296<=$K11)*(1))} -> 0 | BA296: =AW296-AX296 -> 2 | BB296: =AX296-AY296 -> 0 | BC296: =AY296 -> 0 | BE296: =BA296/COUNT($V296:$AN296) -> 0.10526316 | BF296: =BB296/COUNT($V296:$AN296) -> 0 | BG296: =BC296/COUNT($V296:$AN296) -> 0
N297: Centre | O297: BONGOUANOU | P297: Ande | V297: =V12/MEDIAN(Q12:U12) -> 1 | W297: =W12/MEDIAN(R12:V12) -> 1 | X297: =X12/MEDIAN(S12:W12) -> 1 | Y297: =Y12/MEDIAN(T12:X12) -> 1 | Z297: =Z12/MEDIAN(U12:Y12) -> 1 | AA297: =AA12/MEDIAN(V12:Z12) -> 1 | AB297: =AB12/MEDIAN(W12:AA12) -> 1 | AC297: =AC12/MEDIAN(X12:AB12) -> 1 | ... AN297: =AN12/MEDIAN(AI12:AM12) -> 0.99222583 | AS297: {=SUMPRODUCT(($V297:$AN297<=$I12)*(1))/COUNT($V297:$AN297)} -> 0 | AT297: {=SUMPRODUCT(($V297:$AN297<=$J12)*(1))/COUNT($V297:$AN297)} -> 0 | AU297: {=SUMPRODUCT(($V297:$AN297<=$K12)*(1))/COUNT($V297:$AN297)} -> 0 | AW297: {=SUMPRODUCT(($V297:$AN297<=$I12)*(1))} -> 0 | AX297: {=SUMPRODUCT(($V297:$AN297<=$J12)*(1))} -> 0 | AY297: {=SUMPRODUCT(($V297:$AN297<=$K12)*(1))} -> 0 | BA297: =AW297-AX297 -> 0 | BB297: =AX297-AY297 -> 0 | BC297: =AY297 -> 0 | BE297: =BA297/COUNT($V297:$AN297) -> 0 | BF297: =BB297/COUNT($V297:$AN297) -> 0 | BG297: =BC297/COUNT($V297:$AN297) -> 0
N298: Centre | O298: BEOUMI | P298: Ando-Kekrenou | V298: =V13/MEDIAN(Q13:U13) -> 1 | W298: =W13/MEDIAN(R13:V13) -> 0.92058464 | X298: =X13/MEDIAN(S13:W13) -> 1.0018234 | Y298: =Y13/MEDIAN(T13:X13) -> 0.98929726 | Z298: =Z13/MEDIAN(U13:Y13) -> 0.99626106 | AA298: =AA13/MEDIAN(V13:Z13) -> 0.98730246 | AB298: =AB13/MEDIAN(W13:AA13) -> 1.0146121 | AC298: =AC13/MEDIAN(X13:AB13) -> 1.0108185 | ... AN298: =AN13/MEDIAN(AI13:AM13) -> 0.93221932 | AS298: {=SUMPRODUCT(($V298:$AN298<=$I13)*(1))/COUNT($V298:$AN298)} -> 0.15789474 | AT298: {=SUMPRODUCT(($V298:$AN298<=$J13)*(1))/COUNT($V298:$AN298)} -> 0 | AU298: {=SUMPRODUCT(($V298:$AN298<=$K13)*(1))/COUNT($V298:$AN298)} -> 0 | AW298: {=SUMPRODUCT(($V298:$AN298<=$I13)*(1))} -> 3 | AX298: {=SUMPRODUCT(($V298:$AN298<=$J13)*(1))} -> 0 | AY298: {=SUMPRODUCT(($V298:$AN298<=$K13)*(1))} -> 0 | BA298: =AW298-AX298 -> 3 | BB298: =AX298-AY298 -> 0 | BC298: =AY298 -> 0 | BE298: =BA298/COUNT($V298:$AN298) -> 0.15789474 | BF298: =BB298/COUNT($V298:$AN298) -> 0 | BG298: =BC298/COUNT($V298:$AN298) -> 0
N299: Centre | O299: TOUMODI | P299: Angoda | V299: =V14/MEDIAN(Q14:U14) -> 1 | W299: =W14/MEDIAN(R14:V14) -> 1 | X299: =X14/MEDIAN(S14:W14) -> 1 | Y299: =Y14/MEDIAN(T14:X14) -> 1 | Z299: =Z14/MEDIAN(U14:Y14) -> 1 | AA299: =AA14/MEDIAN(V14:Z14) -> 1 | AB299: =AB14/MEDIAN(W14:AA14) -> 1 | AC299: =AC14/MEDIAN(X14:AB14) -> 1 | ... AN299: =AN14/MEDIAN(AI14:AM14) -> 1 | AS299: {=SUMPRODUCT(($V299:$AN299<=$I14)*(1))/COUNT($V299:$AN299)} -> 0 | AT299: {=SUMPRODUCT(($V299:$AN299<=$J14)*(1))/COUNT($V299:$AN299)} -> 0 | AU299: {=SUMPRODUCT(($V299:$AN299<=$K14)*(1))/COUNT($V299:$AN299)} -> 0 | AW299: {=SUMPRODUCT(($V299:$AN299<=$I14)*(1))} -> 0 | AX299: {=SUMPRODUCT(($V299:$AN299<=$J14)*(1))} -> 0 | AY299: {=SUMPRODUCT(($V299:$AN299<=$K14)*(1))} -> 0 | BA299: =AW299-AX299 -> 0 | BB299: =AX299-AY299 -> 0 | BC299: =AY299 -> 0 | BE299: =BA299/COUNT($V299:$AN299) -> 0 | BF299: =BB299/COUNT($V299:$AN299) -> 0 | BG299: =BC299/COUNT($V299:$AN299) -> 0
N300: Centre | O300: PRIKRO | P300: Anianou | V300: =V15/MEDIAN(Q15:U15) -> 1 | W300: =W15/MEDIAN(R15:V15) -> 0.93354219 | X300: =X15/MEDIAN(S15:W15) -> 1.0711889 | Y300: =Y15/MEDIAN(T15:X15) -> 1.0710515 | Z300: =Z15/MEDIAN(U15:Y15) -> 1.0001282 | AA300: =AA15/MEDIAN(V15:Z15) -> 1 | AB300: =AB15/MEDIAN(W15:AA15) -> 1 | AC300: =AC15/MEDIAN(X15:AB15) -> 1 | ... AN300: =AN15/MEDIAN(AI15:AM15) -> 0.85789821 | AS300: {=SUMPRODUCT(($V300:$AN300<=$I15)*(1))/COUNT($V300:$AN300)} -> 0.21052632 | AT300: {=SUMPRODUCT(($V300:$AN300<=$J15)*(1))/COUNT($V300:$AN300)} -> 0 | AU300: {=SUMPRODUCT(($V300:$AN300<=$K15)*(1))/COUNT($V300:$AN300)} -> 0 | AW300: {=SUMPRODUCT(($V300:$AN300<=$I15)*(1))} -> 4 | AX300: {=SUMPRODUCT(($V300:$AN300<=$J15)*(1))} -> 0 | AY300: {=SUMPRODUCT(($V300:$AN300<=$K15)*(1))} -> 0 | BA300: =AW300-AX300 -> 4 | BB300: =AX300-AY300 -> 0 | BC300: =AY300 -> 0 | BE300: =BA300/COUNT($V300:$AN300) -> 0.21052632 | BF300: =BB300/COUNT($V300:$AN300) -> 0 | BG300: =BC300/COUNT($V300:$AN300) -> 0
N301: Centre | O301: M'BATTO | P301: Anoumaba | V301: =V16/MEDIAN(Q16:U16) -> 1 | W301: =W16/MEDIAN(R16:V16) -> 1 | X301: =X16/MEDIAN(S16:W16) -> 1 | Y301: =Y16/MEDIAN(T16:X16) -> 1 | Z301: =Z16/MEDIAN(U16:Y16) -> 1 | AA301: =AA16/MEDIAN(V16:Z16) -> 1 | AB301: =AB16/MEDIAN(W16:AA16) -> 1 | AC301: =AC16/MEDIAN(X16:AB16) -> 1 | ... AN301: =AN16/MEDIAN(AI16:AM16) -> 1 | AS301: {=SUMPRODUCT(($V301:$AN301<=$I16)*(1))/COUNT($V301:$AN301)} -> 0 | AT301: {=SUMPRODUCT(($V301:$AN301<=$J16)*(1))/COUNT($V301:$AN301)} -> 0 | AU301: {=SUMPRODUCT(($V301:$AN301<=$K16)*(1))/COUNT($V301:$AN301)} -> 0 | AW301: {=SUMPRODUCT(($V301:$AN301<=$I16)*(1))} -> 0 | AX301: {=SUMPRODUCT(($V301:$AN301<=$J16)*(1))} -> 0 | AY301: {=SUMPRODUCT(($V301:$AN301<=$K16)*(1))} -> 0 | BA301: =AW301-AX301 -> 0 | BB301: =AX301-AY301 -> 0 | BC301: =AY301 -> 0 | BE301: =BA301/COUNT($V301:$AN301) -> 0 | BF301: =BB301/COUNT($V301:$AN301) -> 0 | BG301: =BC301/COUNT($V301:$AN301) -> 0
N302: Centre | O302: BONDOUKOU | P302: Appimadoum | V302: =V17/MEDIAN(Q17:U17) -> 1 | W302: =W17/MEDIAN(R17:V17) -> 1 | X302: =X17/MEDIAN(S17:W17) -> 1 | Y302: =Y17/MEDIAN(T17:X17) -> 1 | Z302: =Z17/MEDIAN(U17:Y17) -> 1 | AA302: =AA17/MEDIAN(V17:Z17) -> 1 | AB302: =AB17/MEDIAN(W17:AA17) -> 1 | AC302: =AC17/MEDIAN(X17:AB17) -> 0.97575032 | ... AN302: =AN17/MEDIAN(AI17:AM17) -> 1 | AS302: {=SUMPRODUCT(($V302:$AN302<=$I17)*(1))/COUNT($V302:$AN302)} -> 0.052631579 | AT302: {=SUMPRODUCT(($V302:$AN302<=$J17)*(1))/COUNT($V302:$AN302)} -> 0 | AU302: {=SUMPRODUCT(($V302:$AN302<=$K17)*(1))/COUNT($V302:$AN302)} -> 0 | AW302: {=SUMPRODUCT(($V302:$AN302<=$I17)*(1))} -> 1 | AX302: {=SUMPRODUCT(($V302:$AN302<=$J17)*(1))} -> 0 | AY302: {=SUMPRODUCT(($V302:$AN302<=$K17)*(1))} -> 0 | BA302: =AW302-AX302 -> 1 | BB302: =AX302-AY302 -> 0 | BC302: =AY302 -> 0 | BE302: =BA302/COUNT($V302:$AN302) -> 0.052631579 | BF302: =BB302/COUNT($V302:$AN302) -> 0 | BG302: =BC302/COUNT($V302:$AN302) -> 0
N303: Centre | O303: ARRAH | P303: Arrah | V303: =V18/MEDIAN(Q18:U18) -> 1 | W303: =W18/MEDIAN(R18:V18) -> 1 | X303: =X18/MEDIAN(S18:W18) -> 1 | Y303: =Y18/MEDIAN(T18:X18) -> 1 | Z303: =Z18/MEDIAN(U18:Y18) -> 1 | AA303: =AA18/MEDIAN(V18:Z18) -> 1 | AB303: =AB18/MEDIAN(W18:AA18) -> 1 | AC303: =AC18/MEDIAN(X18:AB18) -> 1 | ... AN303: =AN18/MEDIAN(AI18:AM18) -> 0.96026325 | AS303: {=SUMPRODUCT(($V303:$AN303<=$I18)*(1))/COUNT($V303:$AN303)} -> 0 | AT303: {=SUMPRODUCT(($V303:$AN303<=$J18)*(1))/COUNT($V303:$AN303)} -> 0 | AU303: {=SUMPRODUCT(($V303:$AN303<=$K18)*(1))/COUNT($V303:$AN303)} -> 0 | AW303: {=SUMPRODUCT(($V303:$AN303<=$I18)*(1))} -> 0 | AX303: {=SUMPRODUCT(($V303:$AN303<=$J18)*(1))} -> 0 | AY303: {=SUMPRODUCT(($V303:$AN303<=$K18)*(1))} -> 0 | BA303: =AW303-AX303 -> 0 | BB303: =AX303-AY303 -> 0 | BC303: =AY303 -> 0 | BE303: =BA303/COUNT($V303:$AN303) -> 0 | BF303: =BB303/COUNT($V303:$AN303) -> 0 | BG303: =BC303/COUNT($V303:$AN303) -> 0
N304: Centre | O304: M'BATTO | P304: Assahara | V304: =V19/MEDIAN(Q19:U19) -> 1 | W304: =W19/MEDIAN(R19:V19) -> 1 | X304: =X19/MEDIAN(S19:W19) -> 1 | Y304: =Y19/MEDIAN(T19:X19) -> 1 | Z304: =Z19/MEDIAN(U19:Y19) -> 1 | AA304: =AA19/MEDIAN(V19:Z19) -> 1 | AB304: =AB19/MEDIAN(W19:AA19) -> 1 | AC304: =AC19/MEDIAN(X19:AB19) -> 1 | ... AN304: =AN19/MEDIAN(AI19:AM19) -> 1 | AS304: {=SUMPRODUCT(($V304:$AN304<=$I19)*(1))/COUNT($V304:$AN304)} -> 0 | AT304: {=SUMPRODUCT(($V304:$AN304<=$J19)*(1))/COUNT($V304:$AN304)} -> 0 | AU304: {=SUMPRODUCT(($V304:$AN304<=$K19)*(1))/COUNT($V304:$AN304)} -> 0 | AW304: {=SUMPRODUCT(($V304:$AN304<=$I19)*(1))} -> 0 | AX304: {=SUMPRODUCT(($V304:$AN304<=$J19)*(1))} -> 0 | AY304: {=SUMPRODUCT(($V304:$AN304<=$K19)*(1))} -> 0 | BA304: =AW304-AX304 -> 0 | BB304: =AX304-AY304 -> 0 | BC304: =AY304 -> 0 | BE304: =BA304/COUNT($V304:$AN304) -> 0 | BF304: =BB304/COUNT($V304:$AN304) -> 0 | BG304: =BC304/COUNT($V304:$AN304) -> 0
... N527: Nord | O527: TENGRELA | P527: Papara | V527: =V242/MEDIAN(Q242:U242) -> 1 | W527: =W242/MEDIAN(R242:V242) -> 1 | X527: =X242/MEDIAN(S242:W242) -> 1 | Y527: =Y242/MEDIAN(T242:X242) -> 1 | Z527: =Z242/MEDIAN(U242:Y242) -> 1 | AA527: =AA242/MEDIAN(V242:Z242) -> 1 | AB527: =AB242/MEDIAN(W242:AA242) -> 1 | AC527: =AC242/MEDIAN(X242:AB242) -> 1 | ... AN527: =AN242/MEDIAN(AI242:AM242) -> 1 | AS527: {=SUMPRODUCT(($V527:$AN527<=$I242)*(1))/COUNT($V527:$AN527)} -> 0 | AT527: {=SUMPRODUCT(($V527:$AN527<=$J242)*(1))/COUNT($V527:$AN527)} -> 0 | AU527: {=SUMPRODUCT(($V527:$AN527<=$K242)*(1))/COUNT($V527:$AN527)} -> 0 | AW527: {=SUMPRODUCT(($V527:$AN527<=$I242)*(1))} -> 0 | AX527: {=SUMPRODUCT(($V527:$AN527<=$J242)*(1))} -> 0 | AY527: {=SUMPRODUCT(($V527:$AN527<=$K242)*(1))} -> 0 | BA527: =AW527-AX527 -> 0 | BB527: =AX527-AY527 -> 0 | BC527: =AY527 -> 0 | BE527: =BA527/COUNT($V527:$AN527) -> 0 | BF527: =BB527/COUNT($V527:$AN527) -> 0 | BG527: =BC527/COUNT($V527:$AN527) -> 0
N528: Nord | O528: 1 | P528: Parc National de Bouna | V528: =V243/MEDIAN(Q243:U243) -> 1.0731992 | W528: =W243/MEDIAN(R243:V243) -> 0.97928592 | X528: =X243/MEDIAN(S243:W243) -> 1.0914485 | Y528: =Y243/MEDIAN(T243:X243) -> 1.0781845 | Z528: =Z243/MEDIAN(U243:Y243) -> 0.97808772 | AA528: =AA243/MEDIAN(V243:Z243) -> 1.0165967 | AB528: =AB243/MEDIAN(W243:AA243) -> 1.006778 | AC528: =AC243/MEDIAN(X243:AB243) -> 0.84823353 | ... AN528: =AN243/MEDIAN(AI243:AM243) -> 0.83720891 | AS528: {=SUMPRODUCT(($V528:$AN528<=$I243)*(1))/COUNT($V528:$AN528)} -> 0.26315789 | AT528: {=SUMPRODUCT(($V528:$AN528<=$J243)*(1))/COUNT($V528:$AN528)} -> 0.10526316 | AU528: {=SUMPRODUCT(($V528:$AN528<=$K243)*(1))/COUNT($V528:$AN528)} -> 0 | AW528: {=SUMPRODUCT(($V528:$AN528<=$I243)*(1))} -> 5 | AX528: {=SUMPRODUCT(($V528:$AN528<=$J243)*(1))} -> 2 | AY528: {=SUMPRODUCT(($V528:$AN528<=$K243)*(1))} -> 0 | BA528: =AW528-AX528 -> 3 | BB528: =AX528-AY528 -> 2 | BC528: =AY528 -> 0 | BE528: =BA528/COUNT($V528:$AN528) -> 0.15789474 | BF528: =BB528/COUNT($V528:$AN528) -> 0.10526316 | BG528: =BC528/COUNT($V528:$AN528) -> 0
N529: Nord | O529: SINEMATIALI | P529: Sediogo | V529: =V244/MEDIAN(Q244:U244) -> 1 | W529: =W244/MEDIAN(R244:V244) -> 1 | X529: =X244/MEDIAN(S244:W244) -> 1 | Y529: =Y244/MEDIAN(T244:X244) -> 1 | Z529: =Z244/MEDIAN(U244:Y244) -> 1 | AA529: =AA244/MEDIAN(V244:Z244) -> 1 | AB529: =AB244/MEDIAN(W244:AA244) -> 1 | AC529: =AC244/MEDIAN(X244:AB244) -> 1 | ... AN529: =AN244/MEDIAN(AI244:AM244) -> 1 | AS529: {=SUMPRODUCT(($V529:$AN529<=$I244)*(1))/COUNT($V529:$AN529)} -> 0.10526316 | AT529: {=SUMPRODUCT(($V529:$AN529<=$J244)*(1))/COUNT($V529:$AN529)} -> 0 | AU529: {=SUMPRODUCT(($V529:$AN529<=$K244)*(1))/COUNT($V529:$AN529)} -> 0 | AW529: {=SUMPRODUCT(($V529:$AN529<=$I244)*(1))} -> 2 | AX529: {=SUMPRODUCT(($V529:$AN529<=$J244)*(1))} -> 0 | AY529: {=SUMPRODUCT(($V529:$AN529<=$K244)*(1))} -> 0 | BA529: =AW529-AX529 -> 2 | BB529: =AX529-AY529 -> 0 | BC529: =AY529 -> 0 | BE529: =BA529/COUNT($V529:$AN529) -> 0.10526316 | BF529: =BB529/COUNT($V529:$AN529) -> 0 | BG529: =BC529/COUNT($V529:$AN529) -> 0
N530: Nord | O530: SEGUELA | P530: Seguela | V530: =V245/MEDIAN(Q245:U245) -> 1.0379786 | W530: =W245/MEDIAN(R245:V245) -> 0.87615011 | X530: =X245/MEDIAN(S245:W245) -> 1.0413594 | Y530: =Y245/MEDIAN(T245:X245) -> 1.0247228 | Z530: =Z245/MEDIAN(U245:Y245) -> 0.94800236 | AA530: =AA245/MEDIAN(V245:Z245) -> 0.88809937 | AB530: =AB245/MEDIAN(W245:AA245) -> 1.0675555 | AC530: =AC245/MEDIAN(X245:AB245) -> 0.97505579 | ... AN530: =AN245/MEDIAN(AI245:AM245) -> 0.94329784 | AS530: {=SUMPRODUCT(($V530:$AN530<=$I245)*(1))/COUNT($V530:$AN530)} -> 0.36842105 | AT530: {=SUMPRODUCT(($V530:$AN530<=$J245)*(1))/COUNT($V530:$AN530)} -> 0 | AU530: {=SUMPRODUCT(($V530:$AN530<=$K245)*(1))/COUNT($V530:$AN530)} -> 0 | AW530: {=SUMPRODUCT(($V530:$AN530<=$I245)*(1))} -> 7 | AX530: {=SUMPRODUCT(($V530:$AN530<=$J245)*(1))} -> 0 | AY530: {=SUMPRODUCT(($V530:$AN530<=$K245)*(1))} -> 0 | BA530: =AW530-AX530 -> 7 | BB530: =AX530-AY530 -> 0 | BC530: =AY530 -> 0 | BE530: =BA530/COUNT($V530:$AN530) -> 0.36842105 | BF530: =BB530/COUNT($V530:$AN530) -> 0 | BG530: =BC530/COUNT($V530:$AN530) -> 0
N531: Nord | O531: SEGUELON | P531: Seguelon | V531: =V246/MEDIAN(Q246:U246) -> 1 | W531: =W246/MEDIAN(R246:V246) -> 1 | X531: =X246/MEDIAN(S246:W246) -> 1 | Y531: =Y246/MEDIAN(T246:X246) -> 1 | Z531: =Z246/MEDIAN(U246:Y246) -> 1 | AA531: =AA246/MEDIAN(V246:Z246) -> 1 | AB531: =AB246/MEDIAN(W246:AA246) -> 1 | AC531: =AC246/MEDIAN(X246:AB246) -> 1 | ... AN531: =AN246/MEDIAN(AI246:AM246) -> 1 | AS531: {=SUMPRODUCT(($V531:$AN531<=$I246)*(1))/COUNT($V531:$AN531)} -> 0 | AT531: {=SUMPRODUCT(($V531:$AN531<=$J246)*(1))/COUNT($V531:$AN531)} -> 0 | AU531: {=SUMPRODUCT(($V531:$AN531<=$K246)*(1))/COUNT($V531:$AN531)} -> 0 | AW531: {=SUMPRODUCT(($V531:$AN531<=$I246)*(1))} -> 0 | AX531: {=SUMPRODUCT(($V531:$AN531<=$J246)*(1))} -> 0 | AY531: {=SUMPRODUCT(($V531:$AN531<=$K246)*(1))} -> 0 | BA531: =AW531-AX531 -> 0 | BB531: =AX531-AY531 -> 0 | BC531: =AY531 -> 0 | BE531: =BA531/COUNT($V531:$AN531) -> 0 | BF531: =BB531/COUNT($V531:$AN531) -> 0 | BG531: =BC531/COUNT($V531:$AN531) -> 0
N532: Nord | O532: OUANINOU | P532: Saboudougou | V532: =V247/MEDIAN(Q247:U247) -> 1 | W532: =W247/MEDIAN(R247:V247) -> 1 | X532: =X247/MEDIAN(S247:W247) -> 1 | Y532: =Y247/MEDIAN(T247:X247) -> 1 | Z532: =Z247/MEDIAN(U247:Y247) -> 1 | AA532: =AA247/MEDIAN(V247:Z247) -> 1 | AB532: =AB247/MEDIAN(W247:AA247) -> 1 | AC532: =AC247/MEDIAN(X247:AB247) -> 1 | ... AN532: =AN247/MEDIAN(AI247:AM247) -> 1 | AS532: {=SUMPRODUCT(($V532:$AN532<=$I247)*(1))/COUNT($V532:$AN532)} -> 0 | AT532: {=SUMPRODUCT(($V532:$AN532<=$J247)*(1))/COUNT($V532:$AN532)} -> 0 | AU532: {=SUMPRODUCT(($V532:$AN532<=$K247)*(1))/COUNT($V532:$AN532)} -> 0 | AW532: {=SUMPRODUCT(($V532:$AN532<=$I247)*(1))} -> 0 | AX532: {=SUMPRODUCT(($V532:$AN532<=$J247)*(1))} -> 0 | AY532: {=SUMPRODUCT(($V532:$AN532<=$K247)*(1))} -> 0 | BA532: =AW532-AX532 -> 0 | BB532: =AX532-AY532 -> 0 | BC532: =AY532 -> 0 | BE532: =BA532/COUNT($V532:$AN532) -> 0 | BF532: =BB532/COUNT($V532:$AN532) -> 0 | BG532: =BC532/COUNT($V532:$AN532) -> 0
N533: Nord | O533: GBELEBAN | P533: Samango | V533: =V248/MEDIAN(Q248:U248) -> 1 | W533: =W248/MEDIAN(R248:V248) -> 1 | X533: =X248/MEDIAN(S248:W248) -> 1 | Y533: =Y248/MEDIAN(T248:X248) -> 1 | Z533: =Z248/MEDIAN(U248:Y248) -> 1 | AA533: =AA248/MEDIAN(V248:Z248) -> 1 | AB533: =AB248/MEDIAN(W248:AA248) -> 1 | AC533: =AC248/MEDIAN(X248:AB248) -> 1 | ... AN533: =AN248/MEDIAN(AI248:AM248) -> 1 | AS533: {=SUMPRODUCT(($V533:$AN533<=$I248)*(1))/COUNT($V533:$AN533)} -> 0 | AT533: {=SUMPRODUCT(($V533:$AN533<=$J248)*(1))/COUNT($V533:$AN533)} -> 0 | AU533: {=SUMPRODUCT(($V533:$AN533<=$K248)*(1))/COUNT($V533:$AN533)} -> 0 | AW533: {=SUMPRODUCT(($V533:$AN533<=$I248)*(1))} -> 0 | AX533: {=SUMPRODUCT(($V533:$AN533<=$J248)*(1))} -> 0 | AY533: {=SUMPRODUCT(($V533:$AN533<=$K248)*(1))} -> 0 | BA533: =AW533-AX533 -> 0 | BB533: =AX533-AY533 -> 0 | BC533: =AY533 -> 0 | BE533: =BA533/COUNT($V533:$AN533) -> 0 | BF533: =BB533/COUNT($V533:$AN533) -> 0 | BG533: =BC533/COUNT($V533:$AN533) -> 0
N534: Nord | O534: SAMATIGUILA | P534: Samatiguila | V534: =V249/MEDIAN(Q249:U249) -> 1 | W534: =W249/MEDIAN(R249:V249) -> 1 | X534: =X249/MEDIAN(S249:W249) -> 1 | Y534: =Y249/MEDIAN(T249:X249) -> 1 | Z534: =Z249/MEDIAN(U249:Y249) -> 1 | AA534: =AA249/MEDIAN(V249:Z249) -> 1 | AB534: =AB249/MEDIAN(W249:AA249) -> 1 | AC534: =AC249/MEDIAN(X249:AB249) -> 1 | ... AN534: =AN249/MEDIAN(AI249:AM249) -> 1 | AS534: {=SUMPRODUCT(($V534:$AN534<=$I249)*(1))/COUNT($V534:$AN534)} -> 0 | AT534: {=SUMPRODUCT(($V534:$AN534<=$J249)*(1))/COUNT($V534:$AN534)} -> 0 | AU534: {=SUMPRODUCT(($V534:$AN534<=$K249)*(1))/COUNT($V534:$AN534)} -> 0 | AW534: {=SUMPRODUCT(($V534:$AN534<=$I249)*(1))} -> 0 | AX534: {=SUMPRODUCT(($V534:$AN534<=$J249)*(1))} -> 0 | AY534: {=SUMPRODUCT(($V534:$AN534<=$K249)*(1))} -> 0 | BA534: =AW534-AX534 -> 0 | BB534: =AX534-AY534 -> 0 | BC534: =AY534 -> 0 | BE534: =BA534/COUNT($V534:$AN534) -> 0 | BF534: =BB534/COUNT($V534:$AN534) -> 0 | BG534: =BC534/COUNT($V534:$AN534) -> 0
N535: Centre | O535: SANDEGUE | P535: Sandegue | V535: =V250/MEDIAN(Q250:U250) -> 1.1783455 | W535: =W250/MEDIAN(R250:V250) -> 0.96498814 | X535: =X250/MEDIAN(S250:W250) -> 1.2220329 | Y535: =Y250/MEDIAN(T250:X250) -> 1.0320259 | Z535: =Z250/MEDIAN(U250:Y250) -> 1.1841107 | AA535: =AA250/MEDIAN(V250:Z250) -> 1.0741772 | AB535: =AB250/MEDIAN(W250:AA250) -> 1 | AC535: =AC250/MEDIAN(X250:AB250) -> 0.79092851 | ... AN535: =AN250/MEDIAN(AI250:AM250) -> 0.76733815 | AS535: {=SUMPRODUCT(($V535:$AN535<=$I250)*(1))/COUNT($V535:$AN535)} -> 0.26315789 | AT535: {=SUMPRODUCT(($V535:$AN535<=$J250)*(1))/COUNT($V535:$AN535)} -> 0.26315789 | AU535: {=SUMPRODUCT(($V535:$AN535<=$K250)*(1))/COUNT($V535:$AN535)} -> 0.052631579 | AW535: {=SUMPRODUCT(($V535:$AN535<=$I250)*(1))} -> 5 | AX535: {=SUMPRODUCT(($V535:$AN535<=$J250)*(1))} -> 5 | AY535: {=SUMPRODUCT(($V535:$AN535<=$K250)*(1))} -> 1 | BA535: =AW535-AX535 -> 0 | BB535: =AX535-AY535 -> 4 | BC535: =AY535 -> 1 | BE535: =BA535/COUNT($V535:$AN535) -> 0 | BF535: =BB535/COUNT($V535:$AN535) -> 0.21052632 | BG535: =BC535/COUNT($V535:$AN535) -> 0.052631579
N536: Nord | O536: BIANKOUMA | P536: SANTA-BIANKOUMA | V536: =V251/MEDIAN(Q251:U251) -> 1 | W536: =W251/MEDIAN(R251:V251) -> 1 | X536: =X251/MEDIAN(S251:W251) -> 1 | Y536: =Y251/MEDIAN(T251:X251) -> 1 | Z536: =Z251/MEDIAN(U251:Y251) -> 1 | AA536: =AA251/MEDIAN(V251:Z251) -> 1 | AB536: =AB251/MEDIAN(W251:AA251) -> 1 | AC536: =AC251/MEDIAN(X251:AB251) -> 1 | ... AN536: =AN251/MEDIAN(AI251:AM251) -> 1 | AS536: {=SUMPRODUCT(($V536:$AN536<=$I251)*(1))/COUNT($V536:$AN536)} -> 0 | AT536: {=SUMPRODUCT(($V536:$AN536<=$J251)*(1))/COUNT($V536:$AN536)} -> 0 | AU536: {=SUMPRODUCT(($V536:$AN536<=$K251)*(1))/COUNT($V536:$AN536)} -> 0 | AW536: {=SUMPRODUCT(($V536:$AN536<=$I251)*(1))} -> 0 | AX536: {=SUMPRODUCT(($V536:$AN536<=$J251)*(1))} -> 0 | AY536: {=SUMPRODUCT(($V536:$AN536<=$K251)*(1))} -> 0 | BA536: =AW536-AX536 -> 0 | BB536: =AX536-AY536 -> 0 | BC536: =AY536 -> 0 | BE536: =BA536/COUNT($V536:$AN536) -> 0 | BF536: =BB536/COUNT($V536:$AN536) -> 0 | BG536: =BC536/COUNT($V536:$AN536) -> 0
N537: Nord | O537: MANKONO | P537: Sarhala | V537: =V252/MEDIAN(Q252:U252) -> 0.98259588 | W537: =W252/MEDIAN(R252:V252) -> 0.91238986 | X537: =X252/MEDIAN(S252:W252) -> 1.2356874 | Y537: =Y252/MEDIAN(T252:X252) -> 1.0116246 | Z537: =Z252/MEDIAN(U252:Y252) -> 0.79657003 | AA537: =AA252/MEDIAN(V252:Z252) -> 1.0025587 | AB537: =AB252/MEDIAN(W252:AA252) -> 1.1251686 | AC537: =AC252/MEDIAN(X252:AB252) -> 1.1080739 | ... AN537: =AN252/MEDIAN(AI252:AM252) -> 0.96789861 | AS537: {=SUMPRODUCT(($V537:$AN537<=$I252)*(1))/COUNT($V537:$AN537)} -> 0.26315789 | AT537: {=SUMPRODUCT(($V537:$AN537<=$J252)*(1))/COUNT($V537:$AN537)} -> 0.10526316 | AU537: {=SUMPRODUCT(($V537:$AN537<=$K252)*(1))/COUNT($V537:$AN537)} -> 0 | AW537: {=SUMPRODUCT(($V537:$AN537<=$I252)*(1))} -> 5 | AX537: {=SUMPRODUCT(($V537:$AN537<=$J252)*(1))} -> 2 | AY537: {=SUMPRODUCT(($V537:$AN537<=$K252)*(1))} -> 0 | BA537: =AW537-AX537 -> 3 | BB537: =AX537-AY537 -> 2 | BC537: =AY537 -> 0 | BE537: =BA537/COUNT($V537:$AN537) -> 0.15789474 | BF537: =BB537/COUNT($V537:$AN537) -> 0.10526316 | BG537: =BC537/COUNT($V537:$AN537) -> 0
N538: Nord | O538: DABAKALA | P538: Satama-Sokoro | V538: =V253/MEDIAN(Q253:U253) -> 1.0849295 | W538: =W253/MEDIAN(R253:V253) -> 1.0631488 | X538: =X253/MEDIAN(S253:W253) -> 1.1647785 | Y538: =Y253/MEDIAN(T253:X253) -> 0.97572435 | Z538: =Z253/MEDIAN(U253:Y253) -> 1.0144172 | AA538: =AA253/MEDIAN(V253:Z253) -> 1.0065136 | AB538: =AB253/MEDIAN(W253:AA253) -> 1.0055363 | AC538: =AC253/MEDIAN(X253:AB253) -> 0.81657573 | ... AN538: =AN253/MEDIAN(AI253:AM253) -> 0.86718439 | AS538: {=SUMPRODUCT(($V538:$AN538<=$I253)*(1))/COUNT($V538:$AN538)} -> 0.31578947 | AT538: {=SUMPRODUCT(($V538:$AN538<=$J253)*(1))/COUNT($V538:$AN538)} -> 0.21052632 | AU538: {=SUMPRODUCT(($V538:$AN538<=$K253)*(1))/COUNT($V538:$AN538)} -> 0 | AW538: {=SUMPRODUCT(($V538:$AN538<=$I253)*(1))} -> 6 | AX538: {=SUMPRODUCT(($V538:$AN538<=$J253)*(1))} -> 4 | AY538: {=SUMPRODUCT(($V538:$AN538<=$K253)*(1))} -> 0 | BA538: =AW538-AX538 -> 2 | BB538: =AX538-AY538 -> 4 | BC538: =AY538 -> 0 | BE538: =BA538/COUNT($V538:$AN538) -> 0.10526316 | BF538: =BB538/COUNT($V538:$AN538) -> 0.21052632 | BG538: =BC538/COUNT($V538:$AN538) -> 0
N539: Nord | O539: DABAKALA | P539: Satama-Sokoura | V539: =V254/MEDIAN(Q254:U254) -> 1.1128946 | W539: =W254/MEDIAN(R254:V254) -> 0.98529312 | X539: =X254/MEDIAN(S254:W254) -> 1.1242459 | Y539: =Y254/MEDIAN(T254:X254) -> 0.97401782 | Z539: =Z254/MEDIAN(U254:Y254) -> 1.0651634 | AA539: =AA254/MEDIAN(V254:Z254) -> 1.0201422 | AB539: =AB254/MEDIAN(W254:AA254) -> 1.0097098 | AC539: =AC254/MEDIAN(X254:AB254) -> 0.77840438 | ... AN539: =AN254/MEDIAN(AI254:AM254) -> 0.88801073 | AS539: {=SUMPRODUCT(($V539:$AN539<=$I254)*(1))/COUNT($V539:$AN539)} -> 0.31578947 | AT539: {=SUMPRODUCT(($V539:$AN539<=$J254)*(1))/COUNT($V539:$AN539)} -> 0.21052632 | AU539: {=SUMPRODUCT(($V539:$AN539<=$K254)*(1))/COUNT($V539:$AN539)} -> 0 | AW539: {=SUMPRODUCT(($V539:$AN539<=$I254)*(1))} -> 6 | AX539: {=SUMPRODUCT(($V539:$AN539<=$J254)*(1))} -> 4 | AY539: {=SUMPRODUCT(($V539:$AN539<=$K254)*(1))} -> 0 | BA539: =AW539-AX539 -> 2 | BB539: =AX539-AY539 -> 4 | BC539: =AY539 -> 0 | BE539: =BA539/COUNT($V539:$AN539) -> 0.10526316 | BF539: =BB539/COUNT($V539:$AN539) -> 0.21052632 | BG539: =BC539/COUNT($V539:$AN539) -> 0
N540: Nord | O540: GBELEBAN | P540: Seydougou | V540: =V255/MEDIAN(Q255:U255) -> 1 | W540: =W255/MEDIAN(R255:V255) -> 1 | X540: =X255/MEDIAN(S255:W255) -> 1 | Y540: =Y255/MEDIAN(T255:X255) -> 1 | Z540: =Z255/MEDIAN(U255:Y255) -> 1 | AA540: =AA255/MEDIAN(V255:Z255) -> 1 | AB540: =AB255/MEDIAN(W255:AA255) -> 1 | AC540: =AC255/MEDIAN(X255:AB255) -> 1 | ... AN540: =AN255/MEDIAN(AI255:AM255) -> 1 | AS540: {=SUMPRODUCT(($V540:$AN540<=$I255)*(1))/COUNT($V540:$AN540)} -> 0 | AT540: {=SUMPRODUCT(($V540:$AN540<=$J255)*(1))/COUNT($V540:$AN540)} -> 0 | AU540: {=SUMPRODUCT(($V540:$AN540<=$K255)*(1))/COUNT($V540:$AN540)} -> 0 | AW540: {=SUMPRODUCT(($V540:$AN540<=$I255)*(1))} -> 0 | AX540: {=SUMPRODUCT(($V540:$AN540<=$J255)*(1))} -> 0 | AY540: {=SUMPRODUCT(($V540:$AN540<=$K255)*(1))} -> 0 | BA540: =AW540-AX540 -> 0 | BB540: =AX540-AY540 -> 0 | BC540: =AY540 -> 0 | BE540: =BA540/COUNT($V540:$AN540) -> 0 | BF540: =BB540/COUNT($V540:$AN540) -> 0 | BG540: =BC540/COUNT($V540:$AN540) -> 0
... N569: Nord | O569: BOUNA | P569: Youndouo | V569: =V284/MEDIAN(Q284:U284) -> 1.0405225 | W569: =W284/MEDIAN(R284:V284) -> 0.979447 | X569: =X284/MEDIAN(S284:W284) -> 1.0679251 | Y569: =Y284/MEDIAN(T284:X284) -> 1.0459761 | Z569: =Z284/MEDIAN(U284:Y284) -> 1.028476 | AA569: =AA284/MEDIAN(V284:Z284) -> 1.0142498 | AB569: =AB284/MEDIAN(W284:AA284) -> 0.99912799 | AC569: =AC284/MEDIAN(X284:AB284) -> 0.75138277 | ... AN569: =AN284/MEDIAN(AI284:AM284) -> 0.82474686 | AS569: {=SUMPRODUCT(($V569:$AN569<=$I284)*(1))/COUNT($V569:$AN569)} -> 0.26315789 | AT569: {=SUMPRODUCT(($V569:$AN569<=$J284)*(1))/COUNT($V569:$AN569)} -> 0.15789474 | AU569: {=SUMPRODUCT(($V569:$AN569<=$K284)*(1))/COUNT($V569:$AN569)} -> 0 | AW569: {=SUMPRODUCT(($V569:$AN569<=$I284)*(1))} -> 5 | AX569: {=SUMPRODUCT(($V569:$AN569<=$J284)*(1))} -> 3 | AY569: {=SUMPRODUCT(($V569:$AN569<=$K284)*(1))} -> 0 | BA569: =AW569-AX569 -> 2 | BB569: =AX569-AY569 -> 3 | BC569: =AY569 -> 0 | BE569: =BA569/COUNT($V569:$AN569) -> 0.10526316 | BF569: =BB569/COUNT($V569:$AN569) -> 0.15789474 | BG569: =BC569/COUNT($V569:$AN569) -> 0
Q579: WRSI - deviations 2001-2024
N582: Region | O582: District | P582: Sous prefectures | Q582: 2001 | R582: 2002 | S582: 2003 | T582: 2004 | U582: 2005 | V582: 2006 | W582: 2007 | X582: 2008 | Y582: 2009 | Z582: 2010 | AA582: 2011 | AB582: 2012 | AC582: 2013 | AD582: 2014 | AE582: 2015 | AF582: 2016 | AG582: 2017 | AH582: 2018 | AI582: 2019 | AJ582: 2020 | AK582: 2021 | AL582: 2022 | AM582: 2023 | AN582: 2024 | AQ582: Moyenne
N583: Centre | O583: DIMBOKRO | P583: Abigui | V583: =IF(AND(V293<=$I8,V293>$J8),Tarification!$D$8,IF(AND(V293<=$J8,V293>$K8),Tarification!$D$9,IF(AND(V293<=$K8,V293>0),Tarification!$D$10,0))) -> 0 | W583: =IF(AND(W293<=$I8,W293>$J8),Tarification!$D$8,IF(AND(W293<=$J8,W293>$K8),Tarification!$D$9,IF(AND(W293<=$K8,W293>0),Tarification!$D$10,0))) -> 0 | X583: =IF(AND(X293<=$I8,X293>$J8),Tarification!$D$8,IF(AND(X293<=$J8,X293>$K8),Tarification!$D$9,IF(AND(X293<=$K8,X293>0),Tarification!$D$10,0))) -> 0 | Y583: =IF(AND(Y293<=$I8,Y293>$J8),Tarification!$D$8,IF(AND(Y293<=$J8,Y293>$K8),Tarification!$D$9,IF(AND(Y293<=$K8,Y293>0),Tarification!$D$10,0))) -> 0 | Z583: =IF(AND(Z293<=$I8,Z293>$J8),Tarification!$D$8,IF(AND(Z293<=$J8,Z293>$K8),Tarification!$D$9,IF(AND(Z293<=$K8,Z293>0),Tarification!$D$10,0))) -> 0 | AA583: =IF(AND(AA293<=$I8,AA293>$J8),Tarification!$D$8,IF(AND(AA293<=$J8,AA293>$K8),Tarification!$D$9,IF(AND(AA293<=$K8,AA293>0),Tarification!$D$10,0))) -> 0 | AB583: =IF(AND(AB293<=$I8,AB293>$J8),Tarification!$D$8,IF(AND(AB293<=$J8,AB293>$K8),Tarification!$D$9,IF(AND(AB293<=$K8,AB293>0),Tarification!$D$10,0))) -> 0 | AC583: =IF(AND(AC293<=$I8,AC293>$J8),Tarification!$D$8,IF(AND(AC293<=$J8,AC293>$K8),Tarification!$D$9,IF(AND(AC293<=$K8,AC293>0),Tarification!$D$10,0))) -> 0 | ... AN583: =IF(AND(AN293<=$I8,AN293>$J8),Tarification!$D$8,IF(AND(AN293<=$J8,AN293>$K8),Tarification!$D$9,IF(AND(AN293<=$K8,AN293>0),Tarification!$D$10,0))) -> 0 | AQ583: =AVERAGE(V583:AN583) -> 0
N584: Centre | O584: OUELLE | P584: Akpassanou | V584: =IF(AND(V294<=$I9,V294>$J9),Tarification!$D$8,IF(AND(V294<=$J9,V294>$K9),Tarification!$D$9,IF(AND(V294<=$K9,V294>0),Tarification!$D$10,0))) -> 0 | W584: =IF(AND(W294<=$I9,W294>$J9),Tarification!$D$8,IF(AND(W294<=$J9,W294>$K9),Tarification!$D$9,IF(AND(W294<=$K9,W294>0),Tarification!$D$10,0))) -> 50000 | X584: =IF(AND(X294<=$I9,X294>$J9),Tarification!$D$8,IF(AND(X294<=$J9,X294>$K9),Tarification!$D$9,IF(AND(X294<=$K9,X294>0),Tarification!$D$10,0))) -> 0 | Y584: =IF(AND(Y294<=$I9,Y294>$J9),Tarification!$D$8,IF(AND(Y294<=$J9,Y294>$K9),Tarification!$D$9,IF(AND(Y294<=$K9,Y294>0),Tarification!$D$10,0))) -> 0 | Z584: =IF(AND(Z294<=$I9,Z294>$J9),Tarification!$D$8,IF(AND(Z294<=$J9,Z294>$K9),Tarification!$D$9,IF(AND(Z294<=$K9,Z294>0),Tarification!$D$10,0))) -> 0 | AA584: =IF(AND(AA294<=$I9,AA294>$J9),Tarification!$D$8,IF(AND(AA294<=$J9,AA294>$K9),Tarification!$D$9,IF(AND(AA294<=$K9,AA294>0),Tarification!$D$10,0))) -> 0 | AB584: =IF(AND(AB294<=$I9,AB294>$J9),Tarification!$D$8,IF(AND(AB294<=$J9,AB294>$K9),Tarification!$D$9,IF(AND(AB294<=$K9,AB294>0),Tarification!$D$10,0))) -> 0 | AC584: =IF(AND(AC294<=$I9,AC294>$J9),Tarification!$D$8,IF(AND(AC294<=$J9,AC294>$K9),Tarification!$D$9,IF(AND(AC294<=$K9,AC294>0),Tarification!$D$10,0))) -> 0 | ... AN584: =IF(AND(AN294<=$I9,AN294>$J9),Tarification!$D$8,IF(AND(AN294<=$J9,AN294>$K9),Tarification!$D$9,IF(AND(AN294<=$K9,AN294>0),Tarification!$D$10,0))) -> 0 | AQ584: =AVERAGE(V584:AN584) -> 5263.1579
N585: Centre | O585: TANDA | P585: Amanvi | V585: =IF(AND(V295<=$I10,V295>$J10),Tarification!$D$8,IF(AND(V295<=$J10,V295>$K10),Tarification!$D$9,IF(AND(V295<=$K10,V295>0),Tarification!$D$10,0))) -> 0 | W585: =IF(AND(W295<=$I10,W295>$J10),Tarification!$D$8,IF(AND(W295<=$J10,W295>$K10),Tarification!$D$9,IF(AND(W295<=$K10,W295>0),Tarification!$D$10,0))) -> 0 | X585: =IF(AND(X295<=$I10,X295>$J10),Tarification!$D$8,IF(AND(X295<=$J10,X295>$K10),Tarification!$D$9,IF(AND(X295<=$K10,X295>0),Tarification!$D$10,0))) -> 0 | Y585: =IF(AND(Y295<=$I10,Y295>$J10),Tarification!$D$8,IF(AND(Y295<=$J10,Y295>$K10),Tarification!$D$9,IF(AND(Y295<=$K10,Y295>0),Tarification!$D$10,0))) -> 0 | Z585: =IF(AND(Z295<=$I10,Z295>$J10),Tarification!$D$8,IF(AND(Z295<=$J10,Z295>$K10),Tarification!$D$9,IF(AND(Z295<=$K10,Z295>0),Tarification!$D$10,0))) -> 0 | AA585: =IF(AND(AA295<=$I10,AA295>$J10),Tarification!$D$8,IF(AND(AA295<=$J10,AA295>$K10),Tarification!$D$9,IF(AND(AA295<=$K10,AA295>0),Tarification!$D$10,0))) -> 0 | AB585: =IF(AND(AB295<=$I10,AB295>$J10),Tarification!$D$8,IF(AND(AB295<=$J10,AB295>$K10),Tarification!$D$9,IF(AND(AB295<=$K10,AB295>0),Tarification!$D$10,0))) -> 0 | AC585: =IF(AND(AC295<=$I10,AC295>$J10),Tarification!$D$8,IF(AND(AC295<=$J10,AC295>$K10),Tarification!$D$9,IF(AND(AC295<=$K10,AC295>0),Tarification!$D$10,0))) -> 50000 | ... AN585: =IF(AND(AN295<=$I10,AN295>$J10),Tarification!$D$8,IF(AND(AN295<=$J10,AN295>$K10),Tarification!$D$9,IF(AND(AN295<=$K10,AN295>0),Tarification!$D$10,0))) -> 0 | AQ585: =AVERAGE(V585:AN585) -> 11842.105
N586: Centre | O586: OUELLE | P586: Ananda | V586: =IF(AND(V296<=$I11,V296>$J11),Tarification!$D$8,IF(AND(V296<=$J11,V296>$K11),Tarification!$D$9,IF(AND(V296<=$K11,V296>0),Tarification!$D$10,0))) -> 0 | W586: =IF(AND(W296<=$I11,W296>$J11),Tarification!$D$8,IF(AND(W296<=$J11,W296>$K11),Tarification!$D$9,IF(AND(W296<=$K11,W296>0),Tarification!$D$10,0))) -> 50000 | X586: =IF(AND(X296<=$I11,X296>$J11),Tarification!$D$8,IF(AND(X296<=$J11,X296>$K11),Tarification!$D$9,IF(AND(X296<=$K11,X296>0),Tarification!$D$10,0))) -> 0 | Y586: =IF(AND(Y296<=$I11,Y296>$J11),Tarification!$D$8,IF(AND(Y296<=$J11,Y296>$K11),Tarification!$D$9,IF(AND(Y296<=$K11,Y296>0),Tarification!$D$10,0))) -> 0 | Z586: =IF(AND(Z296<=$I11,Z296>$J11),Tarification!$D$8,IF(AND(Z296<=$J11,Z296>$K11),Tarification!$D$9,IF(AND(Z296<=$K11,Z296>0),Tarification!$D$10,0))) -> 0 | AA586: =IF(AND(AA296<=$I11,AA296>$J11),Tarification!$D$8,IF(AND(AA296<=$J11,AA296>$K11),Tarification!$D$9,IF(AND(AA296<=$K11,AA296>0),Tarification!$D$10,0))) -> 0 | AB586: =IF(AND(AB296<=$I11,AB296>$J11),Tarification!$D$8,IF(AND(AB296<=$J11,AB296>$K11),Tarification!$D$9,IF(AND(AB296<=$K11,AB296>0),Tarification!$D$10,0))) -> 0 | AC586: =IF(AND(AC296<=$I11,AC296>$J11),Tarification!$D$8,IF(AND(AC296<=$J11,AC296>$K11),Tarification!$D$9,IF(AND(AC296<=$K11,AC296>0),Tarification!$D$10,0))) -> 0 | ... AN586: =IF(AND(AN296<=$I11,AN296>$J11),Tarification!$D$8,IF(AND(AN296<=$J11,AN296>$K11),Tarification!$D$9,IF(AND(AN296<=$K11,AN296>0),Tarification!$D$10,0))) -> 0 | AQ586: =AVERAGE(V586:AN586) -> 5263.1579
N587: Centre | O587: BONGOUANOU | P587: Ande | V587: =IF(AND(V297<=$I12,V297>$J12),Tarification!$D$8,IF(AND(V297<=$J12,V297>$K12),Tarification!$D$9,IF(AND(V297<=$K12,V297>0),Tarification!$D$10,0))) -> 0 | W587: =IF(AND(W297<=$I12,W297>$J12),Tarification!$D$8,IF(AND(W297<=$J12,W297>$K12),Tarification!$D$9,IF(AND(W297<=$K12,W297>0),Tarification!$D$10,0))) -> 0 | X587: =IF(AND(X297<=$I12,X297>$J12),Tarification!$D$8,IF(AND(X297<=$J12,X297>$K12),Tarification!$D$9,IF(AND(X297<=$K12,X297>0),Tarification!$D$10,0))) -> 0 | Y587: =IF(AND(Y297<=$I12,Y297>$J12),Tarification!$D$8,IF(AND(Y297<=$J12,Y297>$K12),Tarification!$D$9,IF(AND(Y297<=$K12,Y297>0),Tarification!$D$10,0))) -> 0 | Z587: =IF(AND(Z297<=$I12,Z297>$J12),Tarification!$D$8,IF(AND(Z297<=$J12,Z297>$K12),Tarification!$D$9,IF(AND(Z297<=$K12,Z297>0),Tarification!$D$10,0))) -> 0 | AA587: =IF(AND(AA297<=$I12,AA297>$J12),Tarification!$D$8,IF(AND(AA297<=$J12,AA297>$K12),Tarification!$D$9,IF(AND(AA297<=$K12,AA297>0),Tarification!$D$10,0))) -> 0 | AB587: =IF(AND(AB297<=$I12,AB297>$J12),Tarification!$D$8,IF(AND(AB297<=$J12,AB297>$K12),Tarification!$D$9,IF(AND(AB297<=$K12,AB297>0),Tarification!$D$10,0))) -> 0 | AC587: =IF(AND(AC297<=$I12,AC297>$J12),Tarification!$D$8,IF(AND(AC297<=$J12,AC297>$K12),Tarification!$D$9,IF(AND(AC297<=$K12,AC297>0),Tarification!$D$10,0))) -> 0 | ... AN587: =IF(AND(AN297<=$I12,AN297>$J12),Tarification!$D$8,IF(AND(AN297<=$J12,AN297>$K12),Tarification!$D$9,IF(AND(AN297<=$K12,AN297>0),Tarification!$D$10,0))) -> 0 | AQ587: =AVERAGE(V587:AN587) -> 0
N588: Centre | O588: BEOUMI | P588: Ando-Kekrenou | V588: =IF(AND(V298<=$I13,V298>$J13),Tarification!$D$8,IF(AND(V298<=$J13,V298>$K13),Tarification!$D$9,IF(AND(V298<=$K13,V298>0),Tarification!$D$10,0))) -> 0 | W588: =IF(AND(W298<=$I13,W298>$J13),Tarification!$D$8,IF(AND(W298<=$J13,W298>$K13),Tarification!$D$9,IF(AND(W298<=$K13,W298>0),Tarification!$D$10,0))) -> 50000 | X588: =IF(AND(X298<=$I13,X298>$J13),Tarification!$D$8,IF(AND(X298<=$J13,X298>$K13),Tarification!$D$9,IF(AND(X298<=$K13,X298>0),Tarification!$D$10,0))) -> 0 | Y588: =IF(AND(Y298<=$I13,Y298>$J13),Tarification!$D$8,IF(AND(Y298<=$J13,Y298>$K13),Tarification!$D$9,IF(AND(Y298<=$K13,Y298>0),Tarification!$D$10,0))) -> 0 | Z588: =IF(AND(Z298<=$I13,Z298>$J13),Tarification!$D$8,IF(AND(Z298<=$J13,Z298>$K13),Tarification!$D$9,IF(AND(Z298<=$K13,Z298>0),Tarification!$D$10,0))) -> 0 | AA588: =IF(AND(AA298<=$I13,AA298>$J13),Tarification!$D$8,IF(AND(AA298<=$J13,AA298>$K13),Tarification!$D$9,IF(AND(AA298<=$K13,AA298>0),Tarification!$D$10,0))) -> 0 | AB588: =IF(AND(AB298<=$I13,AB298>$J13),Tarification!$D$8,IF(AND(AB298<=$J13,AB298>$K13),Tarification!$D$9,IF(AND(AB298<=$K13,AB298>0),Tarification!$D$10,0))) -> 0 | AC588: =IF(AND(AC298<=$I13,AC298>$J13),Tarification!$D$8,IF(AND(AC298<=$J13,AC298>$K13),Tarification!$D$9,IF(AND(AC298<=$K13,AC298>0),Tarification!$D$10,0))) -> 0 | ... AN588: =IF(AND(AN298<=$I13,AN298>$J13),Tarification!$D$8,IF(AND(AN298<=$J13,AN298>$K13),Tarification!$D$9,IF(AND(AN298<=$K13,AN298>0),Tarification!$D$10,0))) -> 50000 | AQ588: =AVERAGE(V588:AN588) -> 7894.7368
N589: Centre | O589: TOUMODI | P589: Angoda | V589: =IF(AND(V299<=$I14,V299>$J14),Tarification!$D$8,IF(AND(V299<=$J14,V299>$K14),Tarification!$D$9,IF(AND(V299<=$K14,V299>0),Tarification!$D$10,0))) -> 0 | W589: =IF(AND(W299<=$I14,W299>$J14),Tarification!$D$8,IF(AND(W299<=$J14,W299>$K14),Tarification!$D$9,IF(AND(W299<=$K14,W299>0),Tarification!$D$10,0))) -> 0 | X589: =IF(AND(X299<=$I14,X299>$J14),Tarification!$D$8,IF(AND(X299<=$J14,X299>$K14),Tarification!$D$9,IF(AND(X299<=$K14,X299>0),Tarification!$D$10,0))) -> 0 | Y589: =IF(AND(Y299<=$I14,Y299>$J14),Tarification!$D$8,IF(AND(Y299<=$J14,Y299>$K14),Tarification!$D$9,IF(AND(Y299<=$K14,Y299>0),Tarification!$D$10,0))) -> 0 | Z589: =IF(AND(Z299<=$I14,Z299>$J14),Tarification!$D$8,IF(AND(Z299<=$J14,Z299>$K14),Tarification!$D$9,IF(AND(Z299<=$K14,Z299>0),Tarification!$D$10,0))) -> 0 | AA589: =IF(AND(AA299<=$I14,AA299>$J14),Tarification!$D$8,IF(AND(AA299<=$J14,AA299>$K14),Tarification!$D$9,IF(AND(AA299<=$K14,AA299>0),Tarification!$D$10,0))) -> 0 | AB589: =IF(AND(AB299<=$I14,AB299>$J14),Tarification!$D$8,IF(AND(AB299<=$J14,AB299>$K14),Tarification!$D$9,IF(AND(AB299<=$K14,AB299>0),Tarification!$D$10,0))) -> 0 | AC589: =IF(AND(AC299<=$I14,AC299>$J14),Tarification!$D$8,IF(AND(AC299<=$J14,AC299>$K14),Tarification!$D$9,IF(AND(AC299<=$K14,AC299>0),Tarification!$D$10,0))) -> 0 | ... AN589: =IF(AND(AN299<=$I14,AN299>$J14),Tarification!$D$8,IF(AND(AN299<=$J14,AN299>$K14),Tarification!$D$9,IF(AND(AN299<=$K14,AN299>0),Tarification!$D$10,0))) -> 0 | AQ589: =AVERAGE(V589:AN589) -> 0
N590: Centre | O590: PRIKRO | P590: Anianou | V590: =IF(AND(V300<=$I15,V300>$J15),Tarification!$D$8,IF(AND(V300<=$J15,V300>$K15),Tarification!$D$9,IF(AND(V300<=$K15,V300>0),Tarification!$D$10,0))) -> 0 | W590: =IF(AND(W300<=$I15,W300>$J15),Tarification!$D$8,IF(AND(W300<=$J15,W300>$K15),Tarification!$D$9,IF(AND(W300<=$K15,W300>0),Tarification!$D$10,0))) -> 50000 | X590: =IF(AND(X300<=$I15,X300>$J15),Tarification!$D$8,IF(AND(X300<=$J15,X300>$K15),Tarification!$D$9,IF(AND(X300<=$K15,X300>0),Tarification!$D$10,0))) -> 0 | Y590: =IF(AND(Y300<=$I15,Y300>$J15),Tarification!$D$8,IF(AND(Y300<=$J15,Y300>$K15),Tarification!$D$9,IF(AND(Y300<=$K15,Y300>0),Tarification!$D$10,0))) -> 0 | Z590: =IF(AND(Z300<=$I15,Z300>$J15),Tarification!$D$8,IF(AND(Z300<=$J15,Z300>$K15),Tarification!$D$9,IF(AND(Z300<=$K15,Z300>0),Tarification!$D$10,0))) -> 0 | AA590: =IF(AND(AA300<=$I15,AA300>$J15),Tarification!$D$8,IF(AND(AA300<=$J15,AA300>$K15),Tarification!$D$9,IF(AND(AA300<=$K15,AA300>0),Tarification!$D$10,0))) -> 0 | AB590: =IF(AND(AB300<=$I15,AB300>$J15),Tarification!$D$8,IF(AND(AB300<=$J15,AB300>$K15),Tarification!$D$9,IF(AND(AB300<=$K15,AB300>0),Tarification!$D$10,0))) -> 0 | AC590: =IF(AND(AC300<=$I15,AC300>$J15),Tarification!$D$8,IF(AND(AC300<=$J15,AC300>$K15),Tarification!$D$9,IF(AND(AC300<=$K15,AC300>0),Tarification!$D$10,0))) -> 0 | ... AN590: =IF(AND(AN300<=$I15,AN300>$J15),Tarification!$D$8,IF(AND(AN300<=$J15,AN300>$K15),Tarification!$D$9,IF(AND(AN300<=$K15,AN300>0),Tarification!$D$10,0))) -> 50000 | AQ590: =AVERAGE(V590:AN590) -> 10526.316
N591: Centre | O591: M'BATTO | P591: Anoumaba | V591: =IF(AND(V301<=$I16,V301>$J16),Tarification!$D$8,IF(AND(V301<=$J16,V301>$K16),Tarification!$D$9,IF(AND(V301<=$K16,V301>0),Tarification!$D$10,0))) -> 0 | W591: =IF(AND(W301<=$I16,W301>$J16),Tarification!$D$8,IF(AND(W301<=$J16,W301>$K16),Tarification!$D$9,IF(AND(W301<=$K16,W301>0),Tarification!$D$10,0))) -> 0 | X591: =IF(AND(X301<=$I16,X301>$J16),Tarification!$D$8,IF(AND(X301<=$J16,X301>$K16),Tarification!$D$9,IF(AND(X301<=$K16,X301>0),Tarification!$D$10,0))) -> 0 | Y591: =IF(AND(Y301<=$I16,Y301>$J16),Tarification!$D$8,IF(AND(Y301<=$J16,Y301>$K16),Tarification!$D$9,IF(AND(Y301<=$K16,Y301>0),Tarification!$D$10,0))) -> 0 | Z591: =IF(AND(Z301<=$I16,Z301>$J16),Tarification!$D$8,IF(AND(Z301<=$J16,Z301>$K16),Tarification!$D$9,IF(AND(Z301<=$K16,Z301>0),Tarification!$D$10,0))) -> 0 | AA591: =IF(AND(AA301<=$I16,AA301>$J16),Tarification!$D$8,IF(AND(AA301<=$J16,AA301>$K16),Tarification!$D$9,IF(AND(AA301<=$K16,AA301>0),Tarification!$D$10,0))) -> 0 | AB591: =IF(AND(AB301<=$I16,AB301>$J16),Tarification!$D$8,IF(AND(AB301<=$J16,AB301>$K16),Tarification!$D$9,IF(AND(AB301<=$K16,AB301>0),Tarification!$D$10,0))) -> 0 | AC591: =IF(AND(AC301<=$I16,AC301>$J16),Tarification!$D$8,IF(AND(AC301<=$J16,AC301>$K16),Tarification!$D$9,IF(AND(AC301<=$K16,AC301>0),Tarification!$D$10,0))) -> 0 | ... AN591: =IF(AND(AN301<=$I16,AN301>$J16),Tarification!$D$8,IF(AND(AN301<=$J16,AN301>$K16),Tarification!$D$9,IF(AND(AN301<=$K16,AN301>0),Tarification!$D$10,0))) -> 0 | AQ591: =AVERAGE(V591:AN591) -> 0
N592: Centre | O592: BONDOUKOU | P592: Appimadoum | V592: =IF(AND(V302<=$I17,V302>$J17),Tarification!$D$8,IF(AND(V302<=$J17,V302>$K17),Tarification!$D$9,IF(AND(V302<=$K17,V302>0),Tarification!$D$10,0))) -> 0 | W592: =IF(AND(W302<=$I17,W302>$J17),Tarification!$D$8,IF(AND(W302<=$J17,W302>$K17),Tarification!$D$9,IF(AND(W302<=$K17,W302>0),Tarification!$D$10,0))) -> 0 | X592: =IF(AND(X302<=$I17,X302>$J17),Tarification!$D$8,IF(AND(X302<=$J17,X302>$K17),Tarification!$D$9,IF(AND(X302<=$K17,X302>0),Tarification!$D$10,0))) -> 0 | Y592: =IF(AND(Y302<=$I17,Y302>$J17),Tarification!$D$8,IF(AND(Y302<=$J17,Y302>$K17),Tarification!$D$9,IF(AND(Y302<=$K17,Y302>0),Tarification!$D$10,0))) -> 0 | Z592: =IF(AND(Z302<=$I17,Z302>$J17),Tarification!$D$8,IF(AND(Z302<=$J17,Z302>$K17),Tarification!$D$9,IF(AND(Z302<=$K17,Z302>0),Tarification!$D$10,0))) -> 0 | AA592: =IF(AND(AA302<=$I17,AA302>$J17),Tarification!$D$8,IF(AND(AA302<=$J17,AA302>$K17),Tarification!$D$9,IF(AND(AA302<=$K17,AA302>0),Tarification!$D$10,0))) -> 0 | AB592: =IF(AND(AB302<=$I17,AB302>$J17),Tarification!$D$8,IF(AND(AB302<=$J17,AB302>$K17),Tarification!$D$9,IF(AND(AB302<=$K17,AB302>0),Tarification!$D$10,0))) -> 0 | AC592: =IF(AND(AC302<=$I17,AC302>$J17),Tarification!$D$8,IF(AND(AC302<=$J17,AC302>$K17),Tarification!$D$9,IF(AND(AC302<=$K17,AC302>0),Tarification!$D$10,0))) -> 0 | ... AN592: =IF(AND(AN302<=$I17,AN302>$J17),Tarification!$D$8,IF(AND(AN302<=$J17,AN302>$K17),Tarification!$D$9,IF(AND(AN302<=$K17,AN302>0),Tarification!$D$10,0))) -> 0 | AQ592: =AVERAGE(V592:AN592) -> 2631.5789
N593: Centre | O593: ARRAH | P593: Arrah | V593: =IF(AND(V303<=$I18,V303>$J18),Tarification!$D$8,IF(AND(V303<=$J18,V303>$K18),Tarification!$D$9,IF(AND(V303<=$K18,V303>0),Tarification!$D$10,0))) -> 0 | W593: =IF(AND(W303<=$I18,W303>$J18),Tarification!$D$8,IF(AND(W303<=$J18,W303>$K18),Tarification!$D$9,IF(AND(W303<=$K18,W303>0),Tarification!$D$10,0))) -> 0 | X593: =IF(AND(X303<=$I18,X303>$J18),Tarification!$D$8,IF(AND(X303<=$J18,X303>$K18),Tarification!$D$9,IF(AND(X303<=$K18,X303>0),Tarification!$D$10,0))) -> 0 | Y593: =IF(AND(Y303<=$I18,Y303>$J18),Tarification!$D$8,IF(AND(Y303<=$J18,Y303>$K18),Tarification!$D$9,IF(AND(Y303<=$K18,Y303>0),Tarification!$D$10,0))) -> 0 | Z593: =IF(AND(Z303<=$I18,Z303>$J18),Tarification!$D$8,IF(AND(Z303<=$J18,Z303>$K18),Tarification!$D$9,IF(AND(Z303<=$K18,Z303>0),Tarification!$D$10,0))) -> 0 | AA593: =IF(AND(AA303<=$I18,AA303>$J18),Tarification!$D$8,IF(AND(AA303<=$J18,AA303>$K18),Tarification!$D$9,IF(AND(AA303<=$K18,AA303>0),Tarification!$D$10,0))) -> 0 | AB593: =IF(AND(AB303<=$I18,AB303>$J18),Tarification!$D$8,IF(AND(AB303<=$J18,AB303>$K18),Tarification!$D$9,IF(AND(AB303<=$K18,AB303>0),Tarification!$D$10,0))) -> 0 | AC593: =IF(AND(AC303<=$I18,AC303>$J18),Tarification!$D$8,IF(AND(AC303<=$J18,AC303>$K18),Tarification!$D$9,IF(AND(AC303<=$K18,AC303>0),Tarification!$D$10,0))) -> 0 | ... AN593: =IF(AND(AN303<=$I18,AN303>$J18),Tarification!$D$8,IF(AND(AN303<=$J18,AN303>$K18),Tarification!$D$9,IF(AND(AN303<=$K18,AN303>0),Tarification!$D$10,0))) -> 0 | AQ593: =AVERAGE(V593:AN593) -> 0
N594: Centre | O594: M'BATTO | P594: Assahara | V594: =IF(AND(V304<=$I19,V304>$J19),Tarification!$D$8,IF(AND(V304<=$J19,V304>$K19),Tarification!$D$9,IF(AND(V304<=$K19,V304>0),Tarification!$D$10,0))) -> 0 | W594: =IF(AND(W304<=$I19,W304>$J19),Tarification!$D$8,IF(AND(W304<=$J19,W304>$K19),Tarification!$D$9,IF(AND(W304<=$K19,W304>0),Tarification!$D$10,0))) -> 0 | X594: =IF(AND(X304<=$I19,X304>$J19),Tarification!$D$8,IF(AND(X304<=$J19,X304>$K19),Tarification!$D$9,IF(AND(X304<=$K19,X304>0),Tarification!$D$10,0))) -> 0 | Y594: =IF(AND(Y304<=$I19,Y304>$J19),Tarification!$D$8,IF(AND(Y304<=$J19,Y304>$K19),Tarification!$D$9,IF(AND(Y304<=$K19,Y304>0),Tarification!$D$10,0))) -> 0 | Z594: =IF(AND(Z304<=$I19,Z304>$J19),Tarification!$D$8,IF(AND(Z304<=$J19,Z304>$K19),Tarification!$D$9,IF(AND(Z304<=$K19,Z304>0),Tarification!$D$10,0))) -> 0 | AA594: =IF(AND(AA304<=$I19,AA304>$J19),Tarification!$D$8,IF(AND(AA304<=$J19,AA304>$K19),Tarification!$D$9,IF(AND(AA304<=$K19,AA304>0),Tarification!$D$10,0))) -> 0 | AB594: =IF(AND(AB304<=$I19,AB304>$J19),Tarification!$D$8,IF(AND(AB304<=$J19,AB304>$K19),Tarification!$D$9,IF(AND(AB304<=$K19,AB304>0),Tarification!$D$10,0))) -> 0 | AC594: =IF(AND(AC304<=$I19,AC304>$J19),Tarification!$D$8,IF(AND(AC304<=$J19,AC304>$K19),Tarification!$D$9,IF(AND(AC304<=$K19,AC304>0),Tarification!$D$10,0))) -> 0 | ... AN594: =IF(AND(AN304<=$I19,AN304>$J19),Tarification!$D$8,IF(AND(AN304<=$J19,AN304>$K19),Tarification!$D$9,IF(AND(AN304<=$K19,AN304>0),Tarification!$D$10,0))) -> 0 | AQ594: =AVERAGE(V594:AN594) -> 0
... N817: Nord | O817: TENGRELA | P817: Papara | V817: =IF(AND(V527<=$I242,V527>$J242),Tarification!$D$8,IF(AND(V527<=$J242,V527>$K242),Tarification!$D$9,IF(AND(V527<=$K242,V527>0),Tarification!$D$10,0))) -> 0 | W817: =IF(AND(W527<=$I242,W527>$J242),Tarification!$D$8,IF(AND(W527<=$J242,W527>$K242),Tarification!$D$9,IF(AND(W527<=$K242,W527>0),Tarification!$D$10,0))) -> 0 | X817: =IF(AND(X527<=$I242,X527>$J242),Tarification!$D$8,IF(AND(X527<=$J242,X527>$K242),Tarification!$D$9,IF(AND(X527<=$K242,X527>0),Tarification!$D$10,0))) -> 0 | Y817: =IF(AND(Y527<=$I242,Y527>$J242),Tarification!$D$8,IF(AND(Y527<=$J242,Y527>$K242),Tarification!$D$9,IF(AND(Y527<=$K242,Y527>0),Tarification!$D$10,0))) -> 0 | Z817: =IF(AND(Z527<=$I242,Z527>$J242),Tarification!$D$8,IF(AND(Z527<=$J242,Z527>$K242),Tarification!$D$9,IF(AND(Z527<=$K242,Z527>0),Tarification!$D$10,0))) -> 0 | AA817: =IF(AND(AA527<=$I242,AA527>$J242),Tarification!$D$8,IF(AND(AA527<=$J242,AA527>$K242),Tarification!$D$9,IF(AND(AA527<=$K242,AA527>0),Tarification!$D$10,0))) -> 0 | AB817: =IF(AND(AB527<=$I242,AB527>$J242),Tarification!$D$8,IF(AND(AB527<=$J242,AB527>$K242),Tarification!$D$9,IF(AND(AB527<=$K242,AB527>0),Tarification!$D$10,0))) -> 0 | AC817: =IF(AND(AC527<=$I242,AC527>$J242),Tarification!$D$8,IF(AND(AC527<=$J242,AC527>$K242),Tarification!$D$9,IF(AND(AC527<=$K242,AC527>0),Tarification!$D$10,0))) -> 0 | ... AN817: =IF(AND(AN527<=$I242,AN527>$J242),Tarification!$D$8,IF(AND(AN527<=$J242,AN527>$K242),Tarification!$D$9,IF(AND(AN527<=$K242,AN527>0),Tarification!$D$10,0))) -> 0 | AQ817: =AVERAGE(V817:AN817) -> 0
N818: Nord | O818: 1 | P818: Parc National de Bouna | V818: =IF(AND(V528<=$I243,V528>$J243),Tarification!$D$8,IF(AND(V528<=$J243,V528>$K243),Tarification!$D$9,IF(AND(V528<=$K243,V528>0),Tarification!$D$10,0))) -> 0 | W818: =IF(AND(W528<=$I243,W528>$J243),Tarification!$D$8,IF(AND(W528<=$J243,W528>$K243),Tarification!$D$9,IF(AND(W528<=$K243,W528>0),Tarification!$D$10,0))) -> 0 | X818: =IF(AND(X528<=$I243,X528>$J243),Tarification!$D$8,IF(AND(X528<=$J243,X528>$K243),Tarification!$D$9,IF(AND(X528<=$K243,X528>0),Tarification!$D$10,0))) -> 0 | Y818: =IF(AND(Y528<=$I243,Y528>$J243),Tarification!$D$8,IF(AND(Y528<=$J243,Y528>$K243),Tarification!$D$9,IF(AND(Y528<=$K243,Y528>0),Tarification!$D$10,0))) -> 0 | Z818: =IF(AND(Z528<=$I243,Z528>$J243),Tarification!$D$8,IF(AND(Z528<=$J243,Z528>$K243),Tarification!$D$9,IF(AND(Z528<=$K243,Z528>0),Tarification!$D$10,0))) -> 0 | AA818: =IF(AND(AA528<=$I243,AA528>$J243),Tarification!$D$8,IF(AND(AA528<=$J243,AA528>$K243),Tarification!$D$9,IF(AND(AA528<=$K243,AA528>0),Tarification!$D$10,0))) -> 0 | AB818: =IF(AND(AB528<=$I243,AB528>$J243),Tarification!$D$8,IF(AND(AB528<=$J243,AB528>$K243),Tarification!$D$9,IF(AND(AB528<=$K243,AB528>0),Tarification!$D$10,0))) -> 0 | AC818: =IF(AND(AC528<=$I243,AC528>$J243),Tarification!$D$8,IF(AND(AC528<=$J243,AC528>$K243),Tarification!$D$9,IF(AND(AC528<=$K243,AC528>0),Tarification!$D$10,0))) -> 125000 | ... AN818: =IF(AND(AN528<=$I243,AN528>$J243),Tarification!$D$8,IF(AND(AN528<=$J243,AN528>$K243),Tarification!$D$9,IF(AND(AN528<=$K243,AN528>0),Tarification!$D$10,0))) -> 125000 | AQ818: =AVERAGE(V818:AN818) -> 21052.632
N819: Nord | O819: SINEMATIALI | P819: Sediogo | V819: =IF(AND(V529<=$I244,V529>$J244),Tarification!$D$8,IF(AND(V529<=$J244,V529>$K244),Tarification!$D$9,IF(AND(V529<=$K244,V529>0),Tarification!$D$10,0))) -> 0 | W819: =IF(AND(W529<=$I244,W529>$J244),Tarification!$D$8,IF(AND(W529<=$J244,W529>$K244),Tarification!$D$9,IF(AND(W529<=$K244,W529>0),Tarification!$D$10,0))) -> 0 | X819: =IF(AND(X529<=$I244,X529>$J244),Tarification!$D$8,IF(AND(X529<=$J244,X529>$K244),Tarification!$D$9,IF(AND(X529<=$K244,X529>0),Tarification!$D$10,0))) -> 0 | Y819: =IF(AND(Y529<=$I244,Y529>$J244),Tarification!$D$8,IF(AND(Y529<=$J244,Y529>$K244),Tarification!$D$9,IF(AND(Y529<=$K244,Y529>0),Tarification!$D$10,0))) -> 0 | Z819: =IF(AND(Z529<=$I244,Z529>$J244),Tarification!$D$8,IF(AND(Z529<=$J244,Z529>$K244),Tarification!$D$9,IF(AND(Z529<=$K244,Z529>0),Tarification!$D$10,0))) -> 0 | AA819: =IF(AND(AA529<=$I244,AA529>$J244),Tarification!$D$8,IF(AND(AA529<=$J244,AA529>$K244),Tarification!$D$9,IF(AND(AA529<=$K244,AA529>0),Tarification!$D$10,0))) -> 0 | AB819: =IF(AND(AB529<=$I244,AB529>$J244),Tarification!$D$8,IF(AND(AB529<=$J244,AB529>$K244),Tarification!$D$9,IF(AND(AB529<=$K244,AB529>0),Tarification!$D$10,0))) -> 0 | AC819: =IF(AND(AC529<=$I244,AC529>$J244),Tarification!$D$8,IF(AND(AC529<=$J244,AC529>$K244),Tarification!$D$9,IF(AND(AC529<=$K244,AC529>0),Tarification!$D$10,0))) -> 0 | ... AN819: =IF(AND(AN529<=$I244,AN529>$J244),Tarification!$D$8,IF(AND(AN529<=$J244,AN529>$K244),Tarification!$D$9,IF(AND(AN529<=$K244,AN529>0),Tarification!$D$10,0))) -> 0 | AQ819: =AVERAGE(V819:AN819) -> 5263.1579
N820: Nord | O820: SEGUELA | P820: Seguela | V820: =IF(AND(V530<=$I245,V530>$J245),Tarification!$D$8,IF(AND(V530<=$J245,V530>$K245),Tarification!$D$9,IF(AND(V530<=$K245,V530>0),Tarification!$D$10,0))) -> 0 | W820: =IF(AND(W530<=$I245,W530>$J245),Tarification!$D$8,IF(AND(W530<=$J245,W530>$K245),Tarification!$D$9,IF(AND(W530<=$K245,W530>0),Tarification!$D$10,0))) -> 50000 | X820: =IF(AND(X530<=$I245,X530>$J245),Tarification!$D$8,IF(AND(X530<=$J245,X530>$K245),Tarification!$D$9,IF(AND(X530<=$K245,X530>0),Tarification!$D$10,0))) -> 0 | Y820: =IF(AND(Y530<=$I245,Y530>$J245),Tarification!$D$8,IF(AND(Y530<=$J245,Y530>$K245),Tarification!$D$9,IF(AND(Y530<=$K245,Y530>0),Tarification!$D$10,0))) -> 0 | Z820: =IF(AND(Z530<=$I245,Z530>$J245),Tarification!$D$8,IF(AND(Z530<=$J245,Z530>$K245),Tarification!$D$9,IF(AND(Z530<=$K245,Z530>0),Tarification!$D$10,0))) -> 50000 | AA820: =IF(AND(AA530<=$I245,AA530>$J245),Tarification!$D$8,IF(AND(AA530<=$J245,AA530>$K245),Tarification!$D$9,IF(AND(AA530<=$K245,AA530>0),Tarification!$D$10,0))) -> 50000 | AB820: =IF(AND(AB530<=$I245,AB530>$J245),Tarification!$D$8,IF(AND(AB530<=$J245,AB530>$K245),Tarification!$D$9,IF(AND(AB530<=$K245,AB530>0),Tarification!$D$10,0))) -> 0 | AC820: =IF(AND(AC530<=$I245,AC530>$J245),Tarification!$D$8,IF(AND(AC530<=$J245,AC530>$K245),Tarification!$D$9,IF(AND(AC530<=$K245,AC530>0),Tarification!$D$10,0))) -> 0 | ... AN820: =IF(AND(AN530<=$I245,AN530>$J245),Tarification!$D$8,IF(AND(AN530<=$J245,AN530>$K245),Tarification!$D$9,IF(AND(AN530<=$K245,AN530>0),Tarification!$D$10,0))) -> 50000 | AQ820: =AVERAGE(V820:AN820) -> 18421.053
N821: Nord | O821: SEGUELON | P821: Seguelon | V821: =IF(AND(V531<=$I246,V531>$J246),Tarification!$D$8,IF(AND(V531<=$J246,V531>$K246),Tarification!$D$9,IF(AND(V531<=$K246,V531>0),Tarification!$D$10,0))) -> 0 | W821: =IF(AND(W531<=$I246,W531>$J246),Tarification!$D$8,IF(AND(W531<=$J246,W531>$K246),Tarification!$D$9,IF(AND(W531<=$K246,W531>0),Tarification!$D$10,0))) -> 0 | X821: =IF(AND(X531<=$I246,X531>$J246),Tarification!$D$8,IF(AND(X531<=$J246,X531>$K246),Tarification!$D$9,IF(AND(X531<=$K246,X531>0),Tarification!$D$10,0))) -> 0 | Y821: =IF(AND(Y531<=$I246,Y531>$J246),Tarification!$D$8,IF(AND(Y531<=$J246,Y531>$K246),Tarification!$D$9,IF(AND(Y531<=$K246,Y531>0),Tarification!$D$10,0))) -> 0 | Z821: =IF(AND(Z531<=$I246,Z531>$J246),Tarification!$D$8,IF(AND(Z531<=$J246,Z531>$K246),Tarification!$D$9,IF(AND(Z531<=$K246,Z531>0),Tarification!$D$10,0))) -> 0 | AA821: =IF(AND(AA531<=$I246,AA531>$J246),Tarification!$D$8,IF(AND(AA531<=$J246,AA531>$K246),Tarification!$D$9,IF(AND(AA531<=$K246,AA531>0),Tarification!$D$10,0))) -> 0 | AB821: =IF(AND(AB531<=$I246,AB531>$J246),Tarification!$D$8,IF(AND(AB531<=$J246,AB531>$K246),Tarification!$D$9,IF(AND(AB531<=$K246,AB531>0),Tarification!$D$10,0))) -> 0 | AC821: =IF(AND(AC531<=$I246,AC531>$J246),Tarification!$D$8,IF(AND(AC531<=$J246,AC531>$K246),Tarification!$D$9,IF(AND(AC531<=$K246,AC531>0),Tarification!$D$10,0))) -> 0 | ... AN821: =IF(AND(AN531<=$I246,AN531>$J246),Tarification!$D$8,IF(AND(AN531<=$J246,AN531>$K246),Tarification!$D$9,IF(AND(AN531<=$K246,AN531>0),Tarification!$D$10,0))) -> 0 | AQ821: =AVERAGE(V821:AN821) -> 0
N822: Nord | O822: OUANINOU | P822: Saboudougou | V822: =IF(AND(V532<=$I247,V532>$J247),Tarification!$D$8,IF(AND(V532<=$J247,V532>$K247),Tarification!$D$9,IF(AND(V532<=$K247,V532>0),Tarification!$D$10,0))) -> 0 | W822: =IF(AND(W532<=$I247,W532>$J247),Tarification!$D$8,IF(AND(W532<=$J247,W532>$K247),Tarification!$D$9,IF(AND(W532<=$K247,W532>0),Tarification!$D$10,0))) -> 0 | X822: =IF(AND(X532<=$I247,X532>$J247),Tarification!$D$8,IF(AND(X532<=$J247,X532>$K247),Tarification!$D$9,IF(AND(X532<=$K247,X532>0),Tarification!$D$10,0))) -> 0 | Y822: =IF(AND(Y532<=$I247,Y532>$J247),Tarification!$D$8,IF(AND(Y532<=$J247,Y532>$K247),Tarification!$D$9,IF(AND(Y532<=$K247,Y532>0),Tarification!$D$10,0))) -> 0 | Z822: =IF(AND(Z532<=$I247,Z532>$J247),Tarification!$D$8,IF(AND(Z532<=$J247,Z532>$K247),Tarification!$D$9,IF(AND(Z532<=$K247,Z532>0),Tarification!$D$10,0))) -> 0 | AA822: =IF(AND(AA532<=$I247,AA532>$J247),Tarification!$D$8,IF(AND(AA532<=$J247,AA532>$K247),Tarification!$D$9,IF(AND(AA532<=$K247,AA532>0),Tarification!$D$10,0))) -> 0 | AB822: =IF(AND(AB532<=$I247,AB532>$J247),Tarification!$D$8,IF(AND(AB532<=$J247,AB532>$K247),Tarification!$D$9,IF(AND(AB532<=$K247,AB532>0),Tarification!$D$10,0))) -> 0 | AC822: =IF(AND(AC532<=$I247,AC532>$J247),Tarification!$D$8,IF(AND(AC532<=$J247,AC532>$K247),Tarification!$D$9,IF(AND(AC532<=$K247,AC532>0),Tarification!$D$10,0))) -> 0 | ... AN822: =IF(AND(AN532<=$I247,AN532>$J247),Tarification!$D$8,IF(AND(AN532<=$J247,AN532>$K247),Tarification!$D$9,IF(AND(AN532<=$K247,AN532>0),Tarification!$D$10,0))) -> 0 | AQ822: =AVERAGE(V822:AN822) -> 0
N823: Nord | O823: GBELEBAN | P823: Samango | V823: =IF(AND(V533<=$I248,V533>$J248),Tarification!$D$8,IF(AND(V533<=$J248,V533>$K248),Tarification!$D$9,IF(AND(V533<=$K248,V533>0),Tarification!$D$10,0))) -> 0 | W823: =IF(AND(W533<=$I248,W533>$J248),Tarification!$D$8,IF(AND(W533<=$J248,W533>$K248),Tarification!$D$9,IF(AND(W533<=$K248,W533>0),Tarification!$D$10,0))) -> 0 | X823: =IF(AND(X533<=$I248,X533>$J248),Tarification!$D$8,IF(AND(X533<=$J248,X533>$K248),Tarification!$D$9,IF(AND(X533<=$K248,X533>0),Tarification!$D$10,0))) -> 0 | Y823: =IF(AND(Y533<=$I248,Y533>$J248),Tarification!$D$8,IF(AND(Y533<=$J248,Y533>$K248),Tarification!$D$9,IF(AND(Y533<=$K248,Y533>0),Tarification!$D$10,0))) -> 0 | Z823: =IF(AND(Z533<=$I248,Z533>$J248),Tarification!$D$8,IF(AND(Z533<=$J248,Z533>$K248),Tarification!$D$9,IF(AND(Z533<=$K248,Z533>0),Tarification!$D$10,0))) -> 0 | AA823: =IF(AND(AA533<=$I248,AA533>$J248),Tarification!$D$8,IF(AND(AA533<=$J248,AA533>$K248),Tarification!$D$9,IF(AND(AA533<=$K248,AA533>0),Tarification!$D$10,0))) -> 0 | AB823: =IF(AND(AB533<=$I248,AB533>$J248),Tarification!$D$8,IF(AND(AB533<=$J248,AB533>$K248),Tarification!$D$9,IF(AND(AB533<=$K248,AB533>0),Tarification!$D$10,0))) -> 0 | AC823: =IF(AND(AC533<=$I248,AC533>$J248),Tarification!$D$8,IF(AND(AC533<=$J248,AC533>$K248),Tarification!$D$9,IF(AND(AC533<=$K248,AC533>0),Tarification!$D$10,0))) -> 0 | ... AN823: =IF(AND(AN533<=$I248,AN533>$J248),Tarification!$D$8,IF(AND(AN533<=$J248,AN533>$K248),Tarification!$D$9,IF(AND(AN533<=$K248,AN533>0),Tarification!$D$10,0))) -> 0 | AQ823: =AVERAGE(V823:AN823) -> 0
N824: Nord | O824: SAMATIGUILA | P824: Samatiguila | V824: =IF(AND(V534<=$I249,V534>$J249),Tarification!$D$8,IF(AND(V534<=$J249,V534>$K249),Tarification!$D$9,IF(AND(V534<=$K249,V534>0),Tarification!$D$10,0))) -> 0 | W824: =IF(AND(W534<=$I249,W534>$J249),Tarification!$D$8,IF(AND(W534<=$J249,W534>$K249),Tarification!$D$9,IF(AND(W534<=$K249,W534>0),Tarification!$D$10,0))) -> 0 | X824: =IF(AND(X534<=$I249,X534>$J249),Tarification!$D$8,IF(AND(X534<=$J249,X534>$K249),Tarification!$D$9,IF(AND(X534<=$K249,X534>0),Tarification!$D$10,0))) -> 0 | Y824: =IF(AND(Y534<=$I249,Y534>$J249),Tarification!$D$8,IF(AND(Y534<=$J249,Y534>$K249),Tarification!$D$9,IF(AND(Y534<=$K249,Y534>0),Tarification!$D$10,0))) -> 0 | Z824: =IF(AND(Z534<=$I249,Z534>$J249),Tarification!$D$8,IF(AND(Z534<=$J249,Z534>$K249),Tarification!$D$9,IF(AND(Z534<=$K249,Z534>0),Tarification!$D$10,0))) -> 0 | AA824: =IF(AND(AA534<=$I249,AA534>$J249),Tarification!$D$8,IF(AND(AA534<=$J249,AA534>$K249),Tarification!$D$9,IF(AND(AA534<=$K249,AA534>0),Tarification!$D$10,0))) -> 0 | AB824: =IF(AND(AB534<=$I249,AB534>$J249),Tarification!$D$8,IF(AND(AB534<=$J249,AB534>$K249),Tarification!$D$9,IF(AND(AB534<=$K249,AB534>0),Tarification!$D$10,0))) -> 0 | AC824: =IF(AND(AC534<=$I249,AC534>$J249),Tarification!$D$8,IF(AND(AC534<=$J249,AC534>$K249),Tarification!$D$9,IF(AND(AC534<=$K249,AC534>0),Tarification!$D$10,0))) -> 0 | ... AN824: =IF(AND(AN534<=$I249,AN534>$J249),Tarification!$D$8,IF(AND(AN534<=$J249,AN534>$K249),Tarification!$D$9,IF(AND(AN534<=$K249,AN534>0),Tarification!$D$10,0))) -> 0 | AQ824: =AVERAGE(V824:AN824) -> 0
N825: Centre | O825: SANDEGUE | P825: Sandegue | V825: =IF(AND(V535<=$I250,V535>$J250),Tarification!$D$8,IF(AND(V535<=$J250,V535>$K250),Tarification!$D$9,IF(AND(V535<=$K250,V535>0),Tarification!$D$10,0))) -> 0 | W825: =IF(AND(W535<=$I250,W535>$J250),Tarification!$D$8,IF(AND(W535<=$J250,W535>$K250),Tarification!$D$9,IF(AND(W535<=$K250,W535>0),Tarification!$D$10,0))) -> 0 | X825: =IF(AND(X535<=$I250,X535>$J250),Tarification!$D$8,IF(AND(X535<=$J250,X535>$K250),Tarification!$D$9,IF(AND(X535<=$K250,X535>0),Tarification!$D$10,0))) -> 0 | Y825: =IF(AND(Y535<=$I250,Y535>$J250),Tarification!$D$8,IF(AND(Y535<=$J250,Y535>$K250),Tarification!$D$9,IF(AND(Y535<=$K250,Y535>0),Tarification!$D$10,0))) -> 0 | Z825: =IF(AND(Z535<=$I250,Z535>$J250),Tarification!$D$8,IF(AND(Z535<=$J250,Z535>$K250),Tarification!$D$9,IF(AND(Z535<=$K250,Z535>0),Tarification!$D$10,0))) -> 0 | AA825: =IF(AND(AA535<=$I250,AA535>$J250),Tarification!$D$8,IF(AND(AA535<=$J250,AA535>$K250),Tarification!$D$9,IF(AND(AA535<=$K250,AA535>0),Tarification!$D$10,0))) -> 0 | AB825: =IF(AND(AB535<=$I250,AB535>$J250),Tarification!$D$8,IF(AND(AB535<=$J250,AB535>$K250),Tarification!$D$9,IF(AND(AB535<=$K250,AB535>0),Tarification!$D$10,0))) -> 0 | AC825: =IF(AND(AC535<=$I250,AC535>$J250),Tarification!$D$8,IF(AND(AC535<=$J250,AC535>$K250),Tarification!$D$9,IF(AND(AC535<=$K250,AC535>0),Tarification!$D$10,0))) -> 125000 | ... AN825: =IF(AND(AN535<=$I250,AN535>$J250),Tarification!$D$8,IF(AND(AN535<=$J250,AN535>$K250),Tarification!$D$9,IF(AND(AN535<=$K250,AN535>0),Tarification!$D$10,0))) -> 125000 | AQ825: =AVERAGE(V825:AN825) -> 39473.684
N826: Nord | O826: BIANKOUMA | P826: SANTA-BIANKOUMA | V826: =IF(AND(V536<=$I251,V536>$J251),Tarification!$D$8,IF(AND(V536<=$J251,V536>$K251),Tarification!$D$9,IF(AND(V536<=$K251,V536>0),Tarification!$D$10,0))) -> 0 | W826: =IF(AND(W536<=$I251,W536>$J251),Tarification!$D$8,IF(AND(W536<=$J251,W536>$K251),Tarification!$D$9,IF(AND(W536<=$K251,W536>0),Tarification!$D$10,0))) -> 0 | X826: =IF(AND(X536<=$I251,X536>$J251),Tarification!$D$8,IF(AND(X536<=$J251,X536>$K251),Tarification!$D$9,IF(AND(X536<=$K251,X536>0),Tarification!$D$10,0))) -> 0 | Y826: =IF(AND(Y536<=$I251,Y536>$J251),Tarification!$D$8,IF(AND(Y536<=$J251,Y536>$K251),Tarification!$D$9,IF(AND(Y536<=$K251,Y536>0),Tarification!$D$10,0))) -> 0 | Z826: =IF(AND(Z536<=$I251,Z536>$J251),Tarification!$D$8,IF(AND(Z536<=$J251,Z536>$K251),Tarification!$D$9,IF(AND(Z536<=$K251,Z536>0),Tarification!$D$10,0))) -> 0 | AA826: =IF(AND(AA536<=$I251,AA536>$J251),Tarification!$D$8,IF(AND(AA536<=$J251,AA536>$K251),Tarification!$D$9,IF(AND(AA536<=$K251,AA536>0),Tarification!$D$10,0))) -> 0 | AB826: =IF(AND(AB536<=$I251,AB536>$J251),Tarification!$D$8,IF(AND(AB536<=$J251,AB536>$K251),Tarification!$D$9,IF(AND(AB536<=$K251,AB536>0),Tarification!$D$10,0))) -> 0 | AC826: =IF(AND(AC536<=$I251,AC536>$J251),Tarification!$D$8,IF(AND(AC536<=$J251,AC536>$K251),Tarification!$D$9,IF(AND(AC536<=$K251,AC536>0),Tarification!$D$10,0))) -> 0 | ... AN826: =IF(AND(AN536<=$I251,AN536>$J251),Tarification!$D$8,IF(AND(AN536<=$J251,AN536>$K251),Tarification!$D$9,IF(AND(AN536<=$K251,AN536>0),Tarification!$D$10,0))) -> 0 | AQ826: =AVERAGE(V826:AN826) -> 0
N827: Nord | O827: MANKONO | P827: Sarhala | V827: =IF(AND(V537<=$I252,V537>$J252),Tarification!$D$8,IF(AND(V537<=$J252,V537>$K252),Tarification!$D$9,IF(AND(V537<=$K252,V537>0),Tarification!$D$10,0))) -> 0 | W827: =IF(AND(W537<=$I252,W537>$J252),Tarification!$D$8,IF(AND(W537<=$J252,W537>$K252),Tarification!$D$9,IF(AND(W537<=$K252,W537>0),Tarification!$D$10,0))) -> 50000 | X827: =IF(AND(X537<=$I252,X537>$J252),Tarification!$D$8,IF(AND(X537<=$J252,X537>$K252),Tarification!$D$9,IF(AND(X537<=$K252,X537>0),Tarification!$D$10,0))) -> 0 | Y827: =IF(AND(Y537<=$I252,Y537>$J252),Tarification!$D$8,IF(AND(Y537<=$J252,Y537>$K252),Tarification!$D$9,IF(AND(Y537<=$K252,Y537>0),Tarification!$D$10,0))) -> 0 | Z827: =IF(AND(Z537<=$I252,Z537>$J252),Tarification!$D$8,IF(AND(Z537<=$J252,Z537>$K252),Tarification!$D$9,IF(AND(Z537<=$K252,Z537>0),Tarification!$D$10,0))) -> 125000 | AA827: =IF(AND(AA537<=$I252,AA537>$J252),Tarification!$D$8,IF(AND(AA537<=$J252,AA537>$K252),Tarification!$D$9,IF(AND(AA537<=$K252,AA537>0),Tarification!$D$10,0))) -> 0 | AB827: =IF(AND(AB537<=$I252,AB537>$J252),Tarification!$D$8,IF(AND(AB537<=$J252,AB537>$K252),Tarification!$D$9,IF(AND(AB537<=$K252,AB537>0),Tarification!$D$10,0))) -> 0 | AC827: =IF(AND(AC537<=$I252,AC537>$J252),Tarification!$D$8,IF(AND(AC537<=$J252,AC537>$K252),Tarification!$D$9,IF(AND(AC537<=$K252,AC537>0),Tarification!$D$10,0))) -> 0 | ... AN827: =IF(AND(AN537<=$I252,AN537>$J252),Tarification!$D$8,IF(AND(AN537<=$J252,AN537>$K252),Tarification!$D$9,IF(AND(AN537<=$K252,AN537>0),Tarification!$D$10,0))) -> 0 | AQ827: =AVERAGE(V827:AN827) -> 21052.632
N828: Nord | O828: DABAKALA | P828: Satama-Sokoro | V828: =IF(AND(V538<=$I253,V538>$J253),Tarification!$D$8,IF(AND(V538<=$J253,V538>$K253),Tarification!$D$9,IF(AND(V538<=$K253,V538>0),Tarification!$D$10,0))) -> 0 | W828: =IF(AND(W538<=$I253,W538>$J253),Tarification!$D$8,IF(AND(W538<=$J253,W538>$K253),Tarification!$D$9,IF(AND(W538<=$K253,W538>0),Tarification!$D$10,0))) -> 0 | X828: =IF(AND(X538<=$I253,X538>$J253),Tarification!$D$8,IF(AND(X538<=$J253,X538>$K253),Tarification!$D$9,IF(AND(X538<=$K253,X538>0),Tarification!$D$10,0))) -> 0 | Y828: =IF(AND(Y538<=$I253,Y538>$J253),Tarification!$D$8,IF(AND(Y538<=$J253,Y538>$K253),Tarification!$D$9,IF(AND(Y538<=$K253,Y538>0),Tarification!$D$10,0))) -> 0 | Z828: =IF(AND(Z538<=$I253,Z538>$J253),Tarification!$D$8,IF(AND(Z538<=$J253,Z538>$K253),Tarification!$D$9,IF(AND(Z538<=$K253,Z538>0),Tarification!$D$10,0))) -> 0 | AA828: =IF(AND(AA538<=$I253,AA538>$J253),Tarification!$D$8,IF(AND(AA538<=$J253,AA538>$K253),Tarification!$D$9,IF(AND(AA538<=$K253,AA538>0),Tarification!$D$10,0))) -> 0 | AB828: =IF(AND(AB538<=$I253,AB538>$J253),Tarification!$D$8,IF(AND(AB538<=$J253,AB538>$K253),Tarification!$D$9,IF(AND(AB538<=$K253,AB538>0),Tarification!$D$10,0))) -> 0 | AC828: =IF(AND(AC538<=$I253,AC538>$J253),Tarification!$D$8,IF(AND(AC538<=$J253,AC538>$K253),Tarification!$D$9,IF(AND(AC538<=$K253,AC538>0),Tarification!$D$10,0))) -> 125000 | ... AN828: =IF(AND(AN538<=$I253,AN538>$J253),Tarification!$D$8,IF(AND(AN538<=$J253,AN538>$K253),Tarification!$D$9,IF(AND(AN538<=$K253,AN538>0),Tarification!$D$10,0))) -> 50000 | AQ828: =AVERAGE(V828:AN828) -> 31578.947
N829: Nord | O829: DABAKALA | P829: Satama-Sokoura | V829: =IF(AND(V539<=$I254,V539>$J254),Tarification!$D$8,IF(AND(V539<=$J254,V539>$K254),Tarification!$D$9,IF(AND(V539<=$K254,V539>0),Tarification!$D$10,0))) -> 0 | W829: =IF(AND(W539<=$I254,W539>$J254),Tarification!$D$8,IF(AND(W539<=$J254,W539>$K254),Tarification!$D$9,IF(AND(W539<=$K254,W539>0),Tarification!$D$10,0))) -> 0 | X829: =IF(AND(X539<=$I254,X539>$J254),Tarification!$D$8,IF(AND(X539<=$J254,X539>$K254),Tarification!$D$9,IF(AND(X539<=$K254,X539>0),Tarification!$D$10,0))) -> 0 | Y829: =IF(AND(Y539<=$I254,Y539>$J254),Tarification!$D$8,IF(AND(Y539<=$J254,Y539>$K254),Tarification!$D$9,IF(AND(Y539<=$K254,Y539>0),Tarification!$D$10,0))) -> 0 | Z829: =IF(AND(Z539<=$I254,Z539>$J254),Tarification!$D$8,IF(AND(Z539<=$J254,Z539>$K254),Tarification!$D$9,IF(AND(Z539<=$K254,Z539>0),Tarification!$D$10,0))) -> 0 | AA829: =IF(AND(AA539<=$I254,AA539>$J254),Tarification!$D$8,IF(AND(AA539<=$J254,AA539>$K254),Tarification!$D$9,IF(AND(AA539<=$K254,AA539>0),Tarification!$D$10,0))) -> 0 | AB829: =IF(AND(AB539<=$I254,AB539>$J254),Tarification!$D$8,IF(AND(AB539<=$J254,AB539>$K254),Tarification!$D$9,IF(AND(AB539<=$K254,AB539>0),Tarification!$D$10,0))) -> 0 | AC829: =IF(AND(AC539<=$I254,AC539>$J254),Tarification!$D$8,IF(AND(AC539<=$J254,AC539>$K254),Tarification!$D$9,IF(AND(AC539<=$K254,AC539>0),Tarification!$D$10,0))) -> 125000 | ... AN829: =IF(AND(AN539<=$I254,AN539>$J254),Tarification!$D$8,IF(AND(AN539<=$J254,AN539>$K254),Tarification!$D$9,IF(AND(AN539<=$K254,AN539>0),Tarification!$D$10,0))) -> 50000 | AQ829: =AVERAGE(V829:AN829) -> 31578.947
N830: Nord | O830: GBELEBAN | P830: Seydougou | V830: =IF(AND(V540<=$I255,V540>$J255),Tarification!$D$8,IF(AND(V540<=$J255,V540>$K255),Tarification!$D$9,IF(AND(V540<=$K255,V540>0),Tarification!$D$10,0))) -> 0 | W830: =IF(AND(W540<=$I255,W540>$J255),Tarification!$D$8,IF(AND(W540<=$J255,W540>$K255),Tarification!$D$9,IF(AND(W540<=$K255,W540>0),Tarification!$D$10,0))) -> 0 | X830: =IF(AND(X540<=$I255,X540>$J255),Tarification!$D$8,IF(AND(X540<=$J255,X540>$K255),Tarification!$D$9,IF(AND(X540<=$K255,X540>0),Tarification!$D$10,0))) -> 0 | Y830: =IF(AND(Y540<=$I255,Y540>$J255),Tarification!$D$8,IF(AND(Y540<=$J255,Y540>$K255),Tarification!$D$9,IF(AND(Y540<=$K255,Y540>0),Tarification!$D$10,0))) -> 0 | Z830: =IF(AND(Z540<=$I255,Z540>$J255),Tarification!$D$8,IF(AND(Z540<=$J255,Z540>$K255),Tarification!$D$9,IF(AND(Z540<=$K255,Z540>0),Tarification!$D$10,0))) -> 0 | AA830: =IF(AND(AA540<=$I255,AA540>$J255),Tarification!$D$8,IF(AND(AA540<=$J255,AA540>$K255),Tarification!$D$9,IF(AND(AA540<=$K255,AA540>0),Tarification!$D$10,0))) -> 0 | AB830: =IF(AND(AB540<=$I255,AB540>$J255),Tarification!$D$8,IF(AND(AB540<=$J255,AB540>$K255),Tarification!$D$9,IF(AND(AB540<=$K255,AB540>0),Tarification!$D$10,0))) -> 0 | AC830: =IF(AND(AC540<=$I255,AC540>$J255),Tarification!$D$8,IF(AND(AC540<=$J255,AC540>$K255),Tarification!$D$9,IF(AND(AC540<=$K255,AC540>0),Tarification!$D$10,0))) -> 0 | ... AN830: =IF(AND(AN540<=$I255,AN540>$J255),Tarification!$D$8,IF(AND(AN540<=$J255,AN540>$K255),Tarification!$D$9,IF(AND(AN540<=$K255,AN540>0),Tarification!$D$10,0))) -> 0 | AQ830: =AVERAGE(V830:AN830) -> 0
... N859: Nord | O859: BOUNA | P859: Youndouo | V859: =IF(AND(V569<=$I284,V569>$J284),Tarification!$D$8,IF(AND(V569<=$J284,V569>$K284),Tarification!$D$9,IF(AND(V569<=$K284,V569>0),Tarification!$D$10,0))) -> 0 | W859: =IF(AND(W569<=$I284,W569>$J284),Tarification!$D$8,IF(AND(W569<=$J284,W569>$K284),Tarification!$D$9,IF(AND(W569<=$K284,W569>0),Tarification!$D$10,0))) -> 0 | X859: =IF(AND(X569<=$I284,X569>$J284),Tarification!$D$8,IF(AND(X569<=$J284,X569>$K284),Tarification!$D$9,IF(AND(X569<=$K284,X569>0),Tarification!$D$10,0))) -> 0 | Y859: =IF(AND(Y569<=$I284,Y569>$J284),Tarification!$D$8,IF(AND(Y569<=$J284,Y569>$K284),Tarification!$D$9,IF(AND(Y569<=$K284,Y569>0),Tarification!$D$10,0))) -> 0 | Z859: =IF(AND(Z569<=$I284,Z569>$J284),Tarification!$D$8,IF(AND(Z569<=$J284,Z569>$K284),Tarification!$D$9,IF(AND(Z569<=$K284,Z569>0),Tarification!$D$10,0))) -> 0 | AA859: =IF(AND(AA569<=$I284,AA569>$J284),Tarification!$D$8,IF(AND(AA569<=$J284,AA569>$K284),Tarification!$D$9,IF(AND(AA569<=$K284,AA569>0),Tarification!$D$10,0))) -> 0 | AB859: =IF(AND(AB569<=$I284,AB569>$J284),Tarification!$D$8,IF(AND(AB569<=$J284,AB569>$K284),Tarification!$D$9,IF(AND(AB569<=$K284,AB569>0),Tarification!$D$10,0))) -> 0 | AC859: =IF(AND(AC569<=$I284,AC569>$J284),Tarification!$D$8,IF(AND(AC569<=$J284,AC569>$K284),Tarification!$D$9,IF(AND(AC569<=$K284,AC569>0),Tarification!$D$10,0))) -> 125000 | ... AN859: =IF(AND(AN569<=$I284,AN569>$J284),Tarification!$D$8,IF(AND(AN569<=$J284,AN569>$K284),Tarification!$D$9,IF(AND(AN569<=$K284,AN569>0),Tarification!$D$10,0))) -> 125000 | AQ859: =AVERAGE(V859:AN859) -> 25000

Sheet (3) Demographie & Departements
A1: SIM' Assurances
C3: Source: INS
C4: Pop agricole | D4: ='(2) ARV Model'!H3 -> 0.46 | F4: https://agriculture.gouv.fr/cote-divoire-contexte-agricole-et-relations-internationales#:~:text=La%20population%20ivoirienne%20se%20partage,deux%20tiers%20de%20la%20population.
E7: N° | F7: DEPARTEMENT/REGION/DISTRICT | G7: SOUS-PREFECTURE | H7: HOMMES | I7: FEMMES | J7: TOTAL | K7: Population agri
E8: 1 | F8: ABIDJAN | G8: ABOBO | H8: 680421.62 | I8: 659661.11 | J8: 1340082.7 | K8: =ROUND($D$4*J8,0) -> 616438
E9: 2 | F9: ABIDJAN | G9: ADJAME | H9: 180917.19 | I9: 159974.42 | J9: 340891.61 | K9: =ROUND($D$4*J9,0) -> 156810
E10: 3 | F10: ABIDJAN | G10: ATTECOUBE | H10: 163988.65 | I10: 149146.36 | J10: 313135.01 | K10: =ROUND($D$4*J10,0) -> 144042
E11: 4 | F11: ABIDJAN | G11: COCODY | H11: 330016.05 | I11: 362566.46 | J11: 692582.51 | K11: =ROUND($D$4*J11,0) -> 318588
E12: 5 | F12: ABIDJAN | G12: KOUMASSI | H12: 209098.07 | I12: 203184.29 | J12: 412282.36 | K12: =ROUND($D$4*J12,0) -> 189650
E13: 6 | F13: ABIDJAN | G13: MARCORY | H13: 110457.91 | I13: 103603.14 | J13: 214061.05 | K13: =ROUND($D$4*J13,0) -> 98468
E14: 7 | F14: ABIDJAN | G14: PLATEAU | H14: 3634.9941 | I14: 3550.6776 | J14: 7185.6717 | K14: =ROUND($D$4*J14,0) -> 3305
E15: 8 | F15: ABIDJAN | G15: PORT-BOUET | H15: 321725.8 | I15: 297069.59 | J15: 618795.39 | K15: =ROUND($D$4*J15,0) -> 284646
E16: 9 | F16: ABIDJAN | G16: TREICHVILLE | H16: 55910.263 | I16: 50641.552 | J16: 106551.82 | K16: =ROUND($D$4*J16,0) -> 49014
E17: 10 | F17: ABIDJAN | G17: YOPOUGON | H17: 795443.02 | I17: 775621.97 | J17: 1571065 | K17: =ROUND($D$4*J17,0) -> 722690
E18: 11 | F18: ABIDJAN | G18: ANYAMA | H18: 200516.57 | I18: 189075.67 | J18: 389592.23 | K18: =ROUND($D$4*J18,0) -> 179212
E19: 12 | F19: ABIDJAN | G19: BINGERVILLE | H19: 101396.95 | I19: 103259.01 | J19: 204655.96 | K19: =ROUND($D$4*J19,0) -> 94142
... E526: 519 | F526: TEHINI | G526: TOUGBO | H526: 15716.215 | I526: 14865.89 | J526: 30582.105 | K526: =ROUND($D$4*J526,0) -> 14068
